{"NPDESYear": "NULL", "ChangedNAICS": "NULL", "LLYear": "2015", "LatLongSource": "FRS", "ReportedCOMID": "NULL", "NPDESPermit": "NULL", "ReportedReach": "NULL", "PublicContactName": "JAMES LANGA", "FederalAgencyName": "C", "ParentName": "HAWK GROUP OF COMS", "ZIP9": "37086", "NAICS1": {"naicscode": "333120", "name": "Construction Machinery Manufacturing", "1990": {"us_count": 56, "state_count": 2, "us_score_pct": 53, "state_score_pct": 100, "state_pounds_pct": 100, "us_pounds_pct": 21}, "1991": {"us_count": 61, "state_count": 2, "us_score_pct": 60, "state_score_pct": 100, "state_pounds_pct": 50, "us_pounds_pct": 16}, "1992": {"us_count": 62, "state_count": 3, "us_score_pct": 62, "state_score_pct": 100, "state_pounds_pct": 33, "us_pounds_pct": 17}, "1993": {"us_count": 62, "state_count": 3, "us_score_pct": 61, "state_score_pct": 100, "state_pounds_pct": 33, "us_pounds_pct": 19}, "1994": {"us_count": 59, "state_count": 3, "us_score_pct": 54, "state_score_pct": 100, "state_pounds_pct": 33, "us_pounds_pct": 22}, "1995": {"us_count": 62, "state_count": 3, "us_score_pct": 58, "state_score_pct": 100, "state_pounds_pct": 33, "us_pounds_pct": 19}, "1996": {"us_count": 60, "state_count": 4, "us_score_pct": 48, "state_score_pct": 50, "state_pounds_pct": 25, "us_pounds_pct": 16}}, "NAICS2": "NULL", "NAICS3": "NULL", "NAICS4": "NULL", "NAICS5": "NULL", "NAICS6": "NULL", "OutfallLatitude": "NULL", "StackVelocitySource": "SIC 3dig", "StackHeight": 9.7536, "RadialDistance": 1702738, "NearReach": "05130203000722", "OutfallLongitude": "NULL", "AssignedReach": "05130203000722", "Longitude": -86.60786, "FIPS": "47149", "Emissions": {"1990": {"state_score_percentile": 65, "us_pounds_percentile": 31, "TotalPounds": 1806.0, "us_score_percentile": 58, "state_pounds_percentile": 27, "TotalScore": 186.51379699999998, "Submissions": [{"Pounds": 1806.0, "ChemicalNumber": 156, "Chemical": "Copper and copper compounds", "Score": 186.51379699999998, "CASStandard": "7440-50-8"}]}, "1991": {"state_score_percentile": 68, "us_pounds_percentile": 31, "TotalPounds": 1810.0, "us_score_percentile": 60, "state_pounds_percentile": 26, "TotalScore": 193.3759915, "Submissions": [{"Pounds": 1805.0, "ChemicalNumber": 156, "Chemical": "Copper and copper compounds", "Score": 193.337006, "CASStandard": "7440-50-8"}, {"Pounds": 5.0, "ChemicalNumber": 594, "Chemical": "Zinc and zinc compounds", "Score": 0.0389855, "CASStandard": "7440-66-6"}]}, "1992": {"state_score_percentile": 66, "us_pounds_percentile": 32, "TotalPounds": 1710.0, "us_score_percentile": 59, "state_pounds_percentile": 25, "TotalScore": 189.20855749999998, "Submissions": [{"Pounds": 1705.0, "ChemicalNumber": 156, "Chemical": "Copper and copper compounds", "Score": 189.16821499999998, "CASStandard": "7440-50-8"}, {"Pounds": 5.0, "ChemicalNumber": 594, "Chemical": "Zinc and zinc compounds", "Score": 0.0403425, "CASStandard": "7440-66-6"}]}, "1993": {"state_score_percentile": 66, "us_pounds_percentile": 36, "TotalPounds": 2055.0, "us_score_percentile": 59, "state_pounds_percentile": 29, "TotalScore": 209.277394, "Submissions": [{"Pounds": 1805.0, "ChemicalNumber": 156, "Chemical": "Copper and copper compounds", "Score": 207.192424, "CASStandard": "7440-50-8"}, {"Pounds": 250.0, "ChemicalNumber": 594, "Chemical": "Zinc and zinc compounds", "Score": 2.08497, "CASStandard": "7440-66-6"}]}, "1994": {"state_score_percentile": 67, "us_pounds_percentile": 37, "TotalPounds": 2355.0, "us_score_percentile": 60, "state_pounds_percentile": 30, "TotalScore": 251.86545299999997, "Submissions": [{"Pounds": 2105.0, "ChemicalNumber": 156, "Chemical": "Copper and copper compounds", "Score": 249.71263299999998, "CASStandard": "7440-50-8"}, {"Pounds": 250.0, "ChemicalNumber": 594, "Chemical": "Zinc and zinc compounds", "Score": 2.15282, "CASStandard": "7440-66-6"}]}, "1995": {"state_score_percentile": 65, "us_pounds_percentile": 34, "TotalPounds": 2355.0, "us_score_percentile": 58, "state_pounds_percentile": 29, "TotalScore": 260.01251099999996, "Submissions": [{"Pounds": 2105.0, "ChemicalNumber": 156, "Chemical": "Copper and copper compounds", "Score": 257.791841, "CASStandard": "7440-50-8"}, {"Pounds": 250.0, "ChemicalNumber": 594, "Chemical": "Zinc and zinc compounds", "Score": 2.22067, "CASStandard": "7440-66-6"}]}, "1996": {"state_score_percentile": 57, "us_pounds_percentile": 29, "TotalPounds": 1005.0, "us_score_percentile": 53, "state_pounds_percentile": 24, "TotalScore": 126.92005, "Submissions": [{"Pounds": 1005.0, "ChemicalNumber": 156, "Chemical": "Copper and copper compounds", "Score": 126.92005, "CASStandard": "7440-50-8"}]}}, "DUNS": "055829022", "X": 1034, "LLNotes": "NULL", "County": "TN,RUTHERFORD", "NPDESCOMID": "NULL", "DistanceToReach": 155.057536105, "SICCode3Digit": "353", "DerivedSIC": "False", "PublicContactPhone": "2162672550", "ParentDUNS": "NA", "HEM3ID": 13897, "SICCode2Digit": "35", "DistanceToHEM3": 12593.1592455, "STFIPS": "47", "City": "LA VERGNE", "FacilityID": "37086SKWLL1717H", "ReportedReachName": "NULL", "ZIPCODE": "37086", "TribalLandName": "NULL", "FRSID": "NULL", "State": "TN", "Latitude": 36.02132, "NearCOMID": 18401685, "ModeledReleases": "True", "StackDiameterSource": "SIC 3dig", "FacilityNumber": 21294, "StackDiameter": 0.7894, "StackHeightSource": "SIC 3dig", "NAICSCode4Digit": "3331", "Region": 4, "RCRANumber": "TNDO51592509", "OnTribalLand": "False", "OutfallSource": "NULL", "SIC5": "NULL", "SIC4": "NULL", "SIC7": "NULL", "SIC6": "NULL", "SIC1": {"name": "CONSTRUCTION MACHINERY", "1990": {"us_count": 77, "state_count": 3, "us_score_pct": 55, "state_score_pct": 66, "state_pounds_pct": 33, "us_pounds_pct": 16}, "1991": {"us_count": 82, "state_count": 3, "us_score_pct": 62, "state_score_pct": 66, "state_pounds_pct": 33, "us_pounds_pct": 18}, "1992": {"us_count": 86, "state_count": 4, "us_score_pct": 61, "state_score_pct": 75, "state_pounds_pct": 25, "us_pounds_pct": 19}, "1993": {"us_count": 83, "state_count": 4, "us_score_pct": 62, "state_score_pct": 75, "state_pounds_pct": 25, "us_pounds_pct": 22}, "1994": {"us_count": 79, "state_count": 2, "us_score_pct": 55, "state_score_pct": 100, "state_pounds_pct": 50, "us_pounds_pct": 25}, "1995": {"us_count": 81, "state_count": 2, "us_score_pct": 56, "state_score_pct": 100, "state_pounds_pct": 50, "us_pounds_pct": 23}, "1996": {"us_count": 76, "state_count": 3, "us_score_pct": 50, "state_score_pct": 33, "state_pounds_pct": 33, "us_pounds_pct": 19}, "siccode": "3531"}, "SIC3": "NULL", "SIC2": "NULL", "NewIndustryFlag": "False", "NPDESReach": "NULL", "FacilityName": "S. K. WELLMAN CORP.", "Y": 1830, "GridCode": 14, "ChromHexPercent": 0.145, "ReachSource": "Nearest", "StackVelocity": 0.3937, "FederalFacilityFlag": "NULL", "AssignedCOMID": 18401685, "NAICSCode3Digit": "333", "DerivedNAICS": "0", "NHDRegion": 5, "PCT_CH6": 0.145, "Street": "1717 HEIL QUAKER BLVD."}