{"NPDESYear": "NULL", "ChangedNAICS": "NULL", "LLYear": "2015", "LatLongSource": "FRS", "ReportedCOMID": "NULL", "NPDESPermit": "NULL", "ReportedReach": "NULL", "PublicContactName": "VERA PRACHT", "FederalAgencyName": "C", "ParentName": "NA", "ZIP9": "410181876", "NAICS1": {"naicscode": "325412", "name": "Pharmaceutical Preparation Manufacturing"}, "NAICS2": "NULL", "NAICS3": "NULL", "NAICS4": "NULL", "NAICS5": "NULL", "NAICS6": "NULL", "OutfallLatitude": "NULL", "StackVelocitySource": "SIC 3dig", "StackHeight": 11.8872, "RadialDistance": 2079082, "NearReach": "NULL", "OutfallLongitude": "NULL", "AssignedReach": "NULL", "Longitude": -84.59517, "FIPS": "21117", "Emissions": {}, "DUNS": "004237806", "X": 1205, "LLNotes": "NULL", "County": "KY,KENTON", "NPDESCOMID": "NULL", "DistanceToReach": "NULL", "SICCode3Digit": "283", "DerivedSIC": "False", "PublicContactPhone": "6065784570", "ParentDUNS": "NA", "HEM3ID": 93814, "SICCode2Digit": "28", "DistanceToHEM3": 7036.14921819, "STFIPS": "21", "City": "ERLANGER", "FacilityID": "41018CHSTR3208D", "ReportedReachName": "NULL", "ZIPCODE": "41018", "TribalLandName": "NULL", "FRSID": "NULL", "State": "KY", "Latitude": 39.02006, "NearCOMID": "NULL", "ModeledReleases": "False", "StackDiameterSource": "SIC 3dig", "FacilityNumber": 24054, "StackDiameter": 0.3962, "StackHeightSource": "SIC 3dig", "NAICSCode4Digit": "3254", "Region": 4, "RCRANumber": "NA", "OnTribalLand": "False", "OutfallSource": "NULL", "SIC5": "NULL", "SIC4": "NULL", "SIC7": "NULL", "SIC6": "NULL", "SIC1": {"name": "PHARMACEUTICAL PREPARATIONS", "siccode": "2834"}, "SIC3": "NULL", "SIC2": "NULL", "NewIndustryFlag": "False", "NPDESReach": "NULL", "FacilityName": "CHESTER LABORATORIES INC", "Y": 2266, "GridCode": 14, "ChromHexPercent": 0.25, "ReachSource": "NULL", "StackVelocity": 7.0317, "FederalFacilityFlag": "NULL", "AssignedCOMID": "NULL", "NAICSCode3Digit": "325", "DerivedNAICS": "0", "NHDRegion": 5, "PCT_CH6": 0.25, "Street": "3208 DIXIE HWY"}