{"NPDESYear": "NULL", "ChangedNAICS": "NULL", "LLYear": "2015", "LatLongSource": "FRS", "ReportedCOMID": "NULL", "NPDESPermit": "NULL", "ReportedReach": "NULL", "PublicContactName": "JENNIFER WARNER", "FederalAgencyName": "C", "ParentName": "ARGOS USA CORP", "ZIP9": "75067", "NAICS1": {"naicscode": "327320", "name": "Ready-Mix Concrete Manufacturing", "2009": {"us_count": 410, "state_count": 51, "us_score_pct": 50, "state_score_pct": 31, "state_pounds_pct": 47, "us_pounds_pct": 49}, "2010": {"us_count": 408, "state_count": 56, "us_score_pct": 48, "state_score_pct": 28, "state_pounds_pct": 39, "us_pounds_pct": 49}, "2011": {"us_count": 446, "state_count": 91, "us_score_pct": 51, "state_score_pct": 48, "state_pounds_pct": 48, "us_pounds_pct": 50}, "2012": {"us_count": 564, "state_count": 131, "us_score_pct": 38, "state_score_pct": 38, "state_pounds_pct": 32, "us_pounds_pct": 37}, "2013": {"us_count": 713, "state_count": 138, "us_score_pct": 52, "state_score_pct": 50, "state_pounds_pct": 46, "us_pounds_pct": 50}, "2014": {"us_count": 750, "state_count": 147, "us_score_pct": 52, "state_score_pct": 48, "state_pounds_pct": 44, "us_pounds_pct": 49}}, "NAICS2": "NULL", "NAICS3": "NULL", "NAICS4": "NULL", "NAICS5": "NULL", "NAICS6": "NULL", "OutfallLatitude": "NULL", "StackVelocitySource": "SIC 3dig", "StackHeight": 11.5824, "RadialDistance": 1110660, "NearReach": "12030103000019", "OutfallLongitude": "NULL", "AssignedReach": "12030103000019", "Longitude": -96.974176, "FIPS": "48121", "Emissions": {"2009": {"state_score_percentile": 10, "us_pounds_percentile": 3, "TotalPounds": 0.042800000000000005, "us_score_percentile": 10, "state_pounds_percentile": 3, "TotalScore": 0.10853764, "Submissions": [{"Pounds": 0.042800000000000005, "ChemicalNumber": 346, "Chemical": "Lead and lead compounds", "Score": 0.10853764, "CASStandard": "7439-92-1"}]}, "2010": {"state_score_percentile": 10, "us_pounds_percentile": 2, "TotalPounds": 0.0349, "us_score_percentile": 9, "state_pounds_percentile": 3, "TotalScore": 0.0897716, "Submissions": [{"Pounds": 0.0349, "ChemicalNumber": 346, "Chemical": "Lead and lead compounds", "Score": 0.0897716, "CASStandard": "7439-92-1"}]}, "2011": {"state_score_percentile": 11, "us_pounds_percentile": 3, "TotalPounds": 0.038, "us_score_percentile": 10, "state_pounds_percentile": 4, "TotalScore": 0.09936798999999999, "Submissions": [{"Pounds": 0.038, "ChemicalNumber": 346, "Chemical": "Lead and lead compounds", "Score": 0.09936798999999999, "CASStandard": "7439-92-1"}]}, "2012": {"state_score_percentile": 11, "us_pounds_percentile": 3, "TotalPounds": 0.0253, "us_score_percentile": 9, "state_pounds_percentile": 4, "TotalScore": 0.06724132000000001, "Submissions": [{"Pounds": 0.0253, "ChemicalNumber": 346, "Chemical": "Lead and lead compounds", "Score": 0.06724132000000001, "CASStandard": "7439-92-1"}]}, "2013": {"state_score_percentile": 14, "us_pounds_percentile": 4, "TotalPounds": 0.045, "us_score_percentile": 12, "state_pounds_percentile": 6, "TotalScore": 0.12165110999999999, "Submissions": [{"Pounds": 0.045, "ChemicalNumber": 346, "Chemical": "Lead and lead compounds", "Score": 0.12165110999999999, "CASStandard": "7439-92-1"}]}, "2014": {"state_score_percentile": 15, "us_pounds_percentile": 4, "TotalPounds": 0.0465, "us_score_percentile": 12, "state_pounds_percentile": 6, "TotalScore": 0.12751015, "Submissions": [{"Pounds": 0.0465, "ChemicalNumber": 346, "Chemical": "Lead and lead compounds", "Score": 0.12751015, "CASStandard": "7439-92-1"}]}}, "DUNS": "134464705", "X": -112, "LLNotes": "NULL", "County": "TX,DENTON", "NPDESCOMID": "NULL", "DistanceToReach": 1089.93016978, "SICCode3Digit": "327", "DerivedSIC": "True", "PublicContactPhone": "9726210999", "ParentDUNS": "197436652", "HEM3ID": 3927, "SICCode2Digit": "32", "DistanceToHEM3": 15327.0064426, "STFIPS": "48", "City": "LEWISVILLE", "FacilityID": "7506WLWSVL1225S", "ReportedReachName": "NULL", "ZIPCODE": "75067", "TribalLandName": "NULL", "FRSID": "NULL", "State": "TX", "Latitude": 33.0288, "NearCOMID": 1278624, "ModeledReleases": "True", "StackDiameterSource": "SIC 3dig", "FacilityNumber": 45470, "StackDiameter": 0.5182, "StackHeightSource": "SIC 3dig", "NAICSCode4Digit": "3273", "Region": 6, "RCRANumber": "NULL", "OnTribalLand": "False", "OutfallSource": "NULL", "SIC5": "NULL", "SIC4": "NULL", "SIC7": "NULL", "SIC6": "NULL", "SIC1": {"name": "READY-MIXED CONCRETE", "siccode": "3273", "2009": {"us_count": 398, "state_count": 51, "us_score_pct": 50, "state_score_pct": 31, "state_pounds_pct": 47, "us_pounds_pct": 49}, "2010": {"us_count": 389, "state_count": 56, "us_score_pct": 49, "state_score_pct": 28, "state_pounds_pct": 39, "us_pounds_pct": 50}, "2011": {"us_count": 427, "state_count": 91, "us_score_pct": 52, "state_score_pct": 48, "state_pounds_pct": 48, "us_pounds_pct": 52}, "2012": {"us_count": 551, "state_count": 131, "us_score_pct": 38, "state_score_pct": 38, "state_pounds_pct": 32, "us_pounds_pct": 37}, "2013": {"us_count": 697, "state_count": 137, "us_score_pct": 53, "state_score_pct": 49, "state_pounds_pct": 46, "us_pounds_pct": 51}, "2014": {"us_count": 734, "state_count": 146, "us_score_pct": 52, "state_score_pct": 48, "state_pounds_pct": 44, "us_pounds_pct": 50}}, "SIC3": "NULL", "SIC2": "NULL", "NewIndustryFlag": "False", "NPDESReach": "NULL", "FacilityName": "LEWISVILLE PLANT", "Y": 1367, "GridCode": 14, "ChromHexPercent": 0.005, "ReachSource": "Nearest", "StackVelocity": 7.6474, "FederalFacilityFlag": "NULL", "AssignedCOMID": 1278624, "NAICSCode3Digit": "327", "DerivedNAICS": "0", "NHDRegion": 12, "PCT_CH6": 0.005, "Street": "1225 S RAILROAD"}