{"NPDESYear": "NULL", "ChangedNAICS": "NULL", "LLYear": "2015", "LatLongSource": "FRS", "ReportedCOMID": "NULL", "NPDESPermit": "NA", "ReportedReach": "NULL", "PublicContactName": "PAUL A. THOMAS", "FederalAgencyName": "C", "ParentName": "OCCIDENTAL CHEMICAL HOLDING CORP", "ZIP9": "78359", "NAICS1": {"naicscode": "325199", "1988": {"us_count": 366, "state_count": 66, "us_score_pct": 43, "state_score_pct": 30, "state_pounds_pct": 28, "us_pounds_pct": 39}, "1989": {"us_count": 382, "state_count": 67, "us_score_pct": 51, "state_score_pct": 34, "state_pounds_pct": 35, "us_pounds_pct": 46}, "1990": {"us_count": 397, "state_count": 70, "us_score_pct": 58, "state_score_pct": 38, "state_pounds_pct": 42, "us_pounds_pct": 54}, "1991": {"us_count": 405, "state_count": 72, "us_score_pct": 74, "state_score_pct": 62, "state_pounds_pct": 69, "us_pounds_pct": 76}, "1992": {"us_count": 402, "state_count": 72, "us_score_pct": 74, "state_score_pct": 62, "state_pounds_pct": 63, "us_pounds_pct": 74}, "1993": {"us_count": 416, "state_count": 75, "us_score_pct": 75, "state_score_pct": 60, "state_pounds_pct": 69, "us_pounds_pct": 76}, "1994": {"us_count": 426, "state_count": 81, "us_score_pct": 75, "state_score_pct": 62, "state_pounds_pct": 69, "us_pounds_pct": 76}, "1995": {"us_count": 417, "state_count": 82, "us_score_pct": 66, "state_score_pct": 52, "state_pounds_pct": 58, "us_pounds_pct": 64}, "1996": {"us_count": 421, "state_count": 84, "us_score_pct": 67, "state_score_pct": 52, "state_pounds_pct": 59, "us_pounds_pct": 63}, "1997": {"us_count": 423, "state_count": 86, "us_score_pct": 68, "state_score_pct": 54, "state_pounds_pct": 61, "us_pounds_pct": 65}, "1998": {"us_count": 436, "state_count": 91, "us_score_pct": 73, "state_score_pct": 60, "state_pounds_pct": 63, "us_pounds_pct": 70}, "1999": {"us_count": 439, "state_count": 89, "us_score_pct": 72, "state_score_pct": 59, "state_pounds_pct": 60, "us_pounds_pct": 68}, "2000": {"us_count": 451, "state_count": 90, "us_score_pct": 75, "state_score_pct": 62, "state_pounds_pct": 66, "us_pounds_pct": 72}, "2001": {"us_count": 452, "state_count": 92, "us_score_pct": 66, "state_score_pct": 55, "state_pounds_pct": 63, "us_pounds_pct": 71}, "2002": {"us_count": 460, "state_count": 93, "us_score_pct": 67, "state_score_pct": 55, "state_pounds_pct": 54, "us_pounds_pct": 64}, "2003": {"us_count": 454, "state_count": 91, "us_score_pct": 66, "state_score_pct": 56, "state_pounds_pct": 57, "us_pounds_pct": 68}, "2004": {"us_count": 454, "state_count": 96, "us_score_pct": 60, "state_score_pct": 51, "state_pounds_pct": 48, "us_pounds_pct": 60}, "2005": {"us_count": 465, "state_count": 94, "us_score_pct": 61, "state_score_pct": 52, "state_pounds_pct": 51, "us_pounds_pct": 63}, "2006": {"us_count": 472, "state_count": 101, "us_score_pct": 68, "state_score_pct": 59, "state_pounds_pct": 70, "us_pounds_pct": 76}, "2007": {"us_count": 481, "state_count": 102, "us_score_pct": 70, "state_score_pct": 59, "state_pounds_pct": 66, "us_pounds_pct": 75}, "2008": {"us_count": 488, "state_count": 104, "us_score_pct": 69, "state_score_pct": 61, "state_pounds_pct": 62, "us_pounds_pct": 72}, "2009": {"us_count": 481, "state_count": 104, "us_score_pct": 71, "state_score_pct": 64, "state_pounds_pct": 63, "us_pounds_pct": 72}, "2010": {"us_count": 485, "state_count": 104, "us_score_pct": 72, "state_score_pct": 62, "state_pounds_pct": 66, "us_pounds_pct": 73}, "2011": {"us_count": 492, "state_count": 103, "us_score_pct": 86, "state_score_pct": 77, "state_pounds_pct": 73, "us_pounds_pct": 78}, "2012": {"us_count": 493, "state_count": 105, "us_score_pct": 85, "state_score_pct": 77, "state_pounds_pct": 61, "us_pounds_pct": 70}, "2013": {"us_count": 497, "state_count": 103, "us_score_pct": 86, "state_score_pct": 77, "state_pounds_pct": 73, "us_pounds_pct": 80}, "2014": {"us_count": 495, "state_count": 102, "us_score_pct": 87, "state_score_pct": 79, "state_pounds_pct": 74, "us_pounds_pct": 82}, "name": "All Other Basic Organic Chemical Manufacturing"}, "NAICS2": "NULL", "NAICS3": "NULL", "NAICS4": "NULL", "NAICS5": "NULL", "NAICS6": "NULL", "OutfallLatitude": "NULL", "StackVelocitySource": "Fac Spec", "StackHeight": 14.9127, "RadialDistance": 550202, "NearReach": "12110201000043", "OutfallLongitude": "NULL", "AssignedReach": "-1", "Longitude": -97.245983, "FIPS": "48409", "Emissions": {"1988": {"state_score_percentile": 67, "us_pounds_percentile": 49, "TotalPounds": 15700.0, "us_score_percentile": 72, "state_pounds_percentile": 50, "TotalScore": 2028.2704916999996, "Submissions": [{"Pounds": 1810.0, "ChemicalNumber": 531, "Chemical": "Tetrachloroethylene (Perchloroethylene)", "Score": 11.2201753, "CASStandard": "127-18-4"}, {"Pounds": 8072.0, "ChemicalNumber": 115, "Chemical": "Carbon tetrachloride", "Score": 1129.8647999999998, "CASStandard": "56-23-5"}, {"Pounds": 32.0, "ChemicalNumber": 331, "Chemical": "Hydrochloric acid", "Score": 0.0376164, "CASStandard": "7647-01-0"}, {"Pounds": 5786.0, "ChemicalNumber": 124, "Chemical": "Chlorine", "Score": 887.1479, "CASStandard": "7782-50-5"}]}, "1989": {"state_score_percentile": 73, "us_pounds_percentile": 61, "TotalPounds": 26231.0, "us_score_percentile": 78, "state_pounds_percentile": 60, "TotalScore": 5669.53913591, "Submissions": [{"Pounds": 4925.0, "ChemicalNumber": 222, "Chemical": "Dichloroethane, 1,2-", "Score": 3044.8199999999997, "CASStandard": "107-06-2"}, {"Pounds": 3.0, "ChemicalNumber": 63, "Chemical": "Bis(2-chloroethyl)ether", "Score": 23.5605, "CASStandard": "111-44-4"}, {"Pounds": 10564.0, "ChemicalNumber": 115, "Chemical": "Carbon tetrachloride", "Score": 1491.029, "CASStandard": "56-23-5"}, {"Pounds": 1172.0, "ChemicalNumber": 291, "Chemical": "Ethylene", "Score": 0.00409791, "CASStandard": "74-85-1"}, {"Pounds": 2413.0, "ChemicalNumber": 331, "Chemical": "Hydrochloric acid", "Score": 2.8644439999999998, "CASStandard": "7647-01-0"}, {"Pounds": 7150.0, "ChemicalNumber": 124, "Chemical": "Chlorine", "Score": 1107.1077, "CASStandard": "7782-50-5"}, {"Pounds": 4.0, "ChemicalNumber": 566, "Chemical": "Trichloroethane, 1,1,2-", "Score": 0.153394, "CASStandard": "79-00-5"}]}, "1990": {"state_score_percentile": 77, "us_pounds_percentile": 73, "TotalPounds": 43786.0, "us_score_percentile": 82, "state_pounds_percentile": 70, "TotalScore": 8658.054994233398, "Submissions": [{"Pounds": 7765.0, "ChemicalNumber": 222, "Chemical": "Dichloroethane, 1,2-", "Score": 4862.76, "CASStandard": "107-06-2"}, {"Pounds": 4.0, "ChemicalNumber": 63, "Chemical": "Bis(2-chloroethyl)ether", "Score": 31.7943, "CASStandard": "111-44-4"}, {"Pounds": 473.0, "ChemicalNumber": 491, "Chemical": "Propylene (Propene)", "Score": 0.00310628, "CASStandard": "115-07-1"}, {"Pounds": 1.0, "ChemicalNumber": 41, "Chemical": "Asbestos (friable)", "Score": 1096.82, "CASStandard": "1332-21-4"}, {"Pounds": 10258.0, "ChemicalNumber": 115, "Chemical": "Carbon tetrachloride", "Score": 1465.894, "CASStandard": "56-23-5"}, {"Pounds": 6.0, "ChemicalNumber": 140, "Chemical": "Chloroform", "Score": 3.35289, "CASStandard": "67-66-3"}, {"Pounds": 12212.0, "ChemicalNumber": 565, "Chemical": "Trichloroethane, 1,1,1-", "Score": 0.0583076, "CASStandard": "71-55-6"}, {"Pounds": 2334.0, "ChemicalNumber": 291, "Chemical": "Ethylene", "Score": 0.00827038, "CASStandard": "74-85-1"}, {"Pounds": 6.0, "ChemicalNumber": 139, "Chemical": "Chloroethane (Ethyl chloride)", "Score": 1.42734e-05, "CASStandard": "75-00-3"}, {"Pounds": 3078.0, "ChemicalNumber": 331, "Chemical": "Hydrochloric acid", "Score": 3.6832666, "CASStandard": "7647-01-0"}, {"Pounds": 70.0, "ChemicalNumber": 29, "Chemical": "Ammonia", "Score": 0.0162861, "CASStandard": "7664-41-7"}, {"Pounds": 7557.0, "ChemicalNumber": 124, "Chemical": "Chlorine", "Score": 1183.0783, "CASStandard": "7782-50-5"}, {"Pounds": 15.0, "ChemicalNumber": 566, "Chemical": "Trichloroethane, 1,1,2-", "Score": 0.582153, "CASStandard": "79-00-5"}, {"Pounds": 7.0, "ChemicalNumber": 529, "Chemical": "Tetrachloroethane, 1,1,2,2-", "Score": 10.0041, "CASStandard": "79-34-5"}]}, "1991": {"state_score_percentile": 86, "us_pounds_percentile": 92, "TotalPounds": 213378.0, "us_score_percentile": 89, "state_pounds_percentile": 88, "TotalScore": 41273.23060338699, "Submissions": [{"Pounds": 32441.0, "ChemicalNumber": 222, "Chemical": "Dichloroethane, 1,2-", "Score": 20736.27, "CASStandard": "107-06-2"}, {"Pounds": 58.0, "ChemicalNumber": 63, "Chemical": "Bis(2-chloroethyl)ether", "Score": 467.196, "CASStandard": "111-44-4"}, {"Pounds": 21598.0, "ChemicalNumber": 491, "Chemical": "Propylene (Propene)", "Score": 0.143818, "CASStandard": "115-07-1"}, {"Pounds": 106.0, "ChemicalNumber": 145, "Chemical": "Chloroprene", "Score": 666.633, "CASStandard": "126-99-8"}, {"Pounds": 5752.0, "ChemicalNumber": 531, "Chemical": "Tetrachloroethylene (Perchloroethylene)", "Score": 36.84664, "CASStandard": "127-18-4"}, {"Pounds": 3.0, "ChemicalNumber": 41, "Chemical": "Asbestos (friable)", "Score": 3327.3, "CASStandard": "1332-21-4"}, {"Pounds": 51.0, "ChemicalNumber": 223, "Chemical": "Dichloroethylene, 1,2-", "Score": 0.0374247, "CASStandard": "540-59-0"}, {"Pounds": 91745.0, "ChemicalNumber": 115, "Chemical": "Carbon tetrachloride", "Score": 13130.24, "CASStandard": "56-23-5"}, {"Pounds": 123.0, "ChemicalNumber": 140, "Chemical": "Chloroform", "Score": 69.6498, "CASStandard": "67-66-3"}, {"Pounds": 14.0, "ChemicalNumber": 323, "Chemical": "Hexachloroethane", "Score": 1.35482, "CASStandard": "67-72-1"}, {"Pounds": 60.0, "ChemicalNumber": 51, "Chemical": "Benzene", "Score": 11.4816, "CASStandard": "71-43-2"}, {"Pounds": 9207.0, "ChemicalNumber": 565, "Chemical": "Trichloroethane, 1,1,1-", "Score": 0.0445453, "CASStandard": "71-55-6"}, {"Pounds": 16178.0, "ChemicalNumber": 291, "Chemical": "Ethylene", "Score": 0.058033, "CASStandard": "74-85-1"}, {"Pounds": 283.0, "ChemicalNumber": 139, "Chemical": "Chloroethane (Ethyl chloride)", "Score": 0.000682201, "CASStandard": "75-00-3"}, {"Pounds": 4685.0, "ChemicalNumber": 586, "Chemical": "Vinyl chloride", "Score": 943.242, "CASStandard": "75-01-4"}, {"Pounds": 5.0, "ChemicalNumber": 587, "Chemical": "Vinylidene chloride", "Score": 0.000564916, "CASStandard": "75-35-4"}, {"Pounds": 15972.0, "ChemicalNumber": 331, "Chemical": "Hydrochloric acid", "Score": 19.32525377, "CASStandard": "7647-01-0"}, {"Pounds": 3215.0, "ChemicalNumber": 29, "Chemical": "Ammonia", "Score": 0.756374, "CASStandard": "7664-41-7"}, {"Pounds": 11764.0, "ChemicalNumber": 124, "Chemical": "Chlorine", "Score": 1846.791, "CASStandard": "7782-50-5"}, {"Pounds": 88.0, "ChemicalNumber": 566, "Chemical": "Trichloroethane, 1,1,2-", "Score": 3.4608, "CASStandard": "79-00-5"}, {"Pounds": 22.0, "ChemicalNumber": 567, "Chemical": "Trichloroethylene", "Score": 2.206256, "CASStandard": "79-01-6"}, {"Pounds": 7.0, "ChemicalNumber": 529, "Chemical": "Tetrachloroethane, 1,1,2,2-", "Score": 10.1374, "CASStandard": "79-34-5"}, {"Pounds": 1.0, "ChemicalNumber": 320, "Chemical": "Hexachloro-1,3-butadiene", "Score": 0.0545915, "CASStandard": "87-68-3"}]}, "1992": {"state_score_percentile": 86, "us_pounds_percentile": 90, "TotalPounds": 169635.0, "us_score_percentile": 89, "state_pounds_percentile": 86, "TotalScore": 35723.5749552127, "Submissions": [{"Pounds": 25240.0, "ChemicalNumber": 222, "Chemical": "Dichloroethane, 1,2-", "Score": 16324.76, "CASStandard": "107-06-2"}, {"Pounds": 89.0, "ChemicalNumber": 135, "Chemical": "Chlorobenzene", "Score": 0.00216593, "CASStandard": "108-90-7"}, {"Pounds": 103.0, "ChemicalNumber": 63, "Chemical": "Bis(2-chloroethyl)ether", "Score": 840.648, "CASStandard": "111-44-4"}, {"Pounds": 21600.0, "ChemicalNumber": 491, "Chemical": "Propylene (Propene)", "Score": 0.145811, "CASStandard": "115-07-1"}, {"Pounds": 43.0, "ChemicalNumber": 145, "Chemical": "Chloroprene", "Score": 274.127, "CASStandard": "126-99-8"}, {"Pounds": 5789.0, "ChemicalNumber": 531, "Chemical": "Tetrachloroethylene (Perchloroethylene)", "Score": 37.56575, "CASStandard": "127-18-4"}, {"Pounds": 3.0, "ChemicalNumber": 41, "Chemical": "Asbestos (friable)", "Score": 3364.15, "CASStandard": "1332-21-4"}, {"Pounds": 152.0, "ChemicalNumber": 223, "Chemical": "Dichloroethylene, 1,2-", "Score": 0.11354159999999999, "CASStandard": "540-59-0"}, {"Pounds": 85962.0, "ChemicalNumber": 115, "Chemical": "Carbon tetrachloride", "Score": 12451.17, "CASStandard": "56-23-5"}, {"Pounds": 3.0, "ChemicalNumber": 364, "Chemical": "Methanol", "Score": 3.7487e-06, "CASStandard": "67-56-1"}, {"Pounds": 395.0, "ChemicalNumber": 140, "Chemical": "Chloroform", "Score": 226.612, "CASStandard": "67-66-3"}, {"Pounds": 1.0, "ChemicalNumber": 323, "Chemical": "Hexachloroethane", "Score": 0.0980445, "CASStandard": "67-72-1"}, {"Pounds": 7.0, "ChemicalNumber": 51, "Chemical": "Benzene", "Score": 1.35716, "CASStandard": "71-43-2"}, {"Pounds": 8800.0, "ChemicalNumber": 565, "Chemical": "Trichloroethane, 1,1,1-", "Score": 0.0431357, "CASStandard": "71-55-6"}, {"Pounds": 145.0, "ChemicalNumber": 291, "Chemical": "Ethylene", "Score": 0.000527085, "CASStandard": "74-85-1"}, {"Pounds": 101.0, "ChemicalNumber": 139, "Chemical": "Chloroethane (Ethyl chloride)", "Score": 0.000246673, "CASStandard": "75-00-3"}, {"Pounds": 753.0, "ChemicalNumber": 586, "Chemical": "Vinyl chloride", "Score": 153.58724, "CASStandard": "75-01-4"}, {"Pounds": 4.0, "ChemicalNumber": 587, "Chemical": "Vinylidene chloride", "Score": 0.000457996, "CASStandard": "75-35-4"}, {"Pounds": 4127.0, "ChemicalNumber": 331, "Chemical": "Hydrochloric acid", "Score": 5.0516152, "CASStandard": "7647-01-0"}, {"Pounds": 3240.0, "ChemicalNumber": 29, "Chemical": "Ammonia", "Score": 0.77087678, "CASStandard": "7664-41-7"}, {"Pounds": 12608.0, "ChemicalNumber": 124, "Chemical": "Chlorine", "Score": 2005.591, "CASStandard": "7782-50-5"}, {"Pounds": 426.0, "ChemicalNumber": 566, "Chemical": "Trichloroethane, 1,1,2-", "Score": 16.9737, "CASStandard": "79-00-5"}, {"Pounds": 31.0, "ChemicalNumber": 567, "Chemical": "Trichloroethylene", "Score": 3.14457, "CASStandard": "79-01-6"}, {"Pounds": 12.0, "ChemicalNumber": 529, "Chemical": "Tetrachloroethane, 1,1,2,2-", "Score": 17.6068, "CASStandard": "79-34-5"}, {"Pounds": 1.0, "ChemicalNumber": 320, "Chemical": "Hexachloro-1,3-butadiene", "Score": 0.055309, "CASStandard": "87-68-3"}]}, "1993": {"state_score_percentile": 84, "us_pounds_percentile": 91, "TotalPounds": 180827.0, "us_score_percentile": 89, "state_pounds_percentile": 88, "TotalScore": 32552.841379297413, "Submissions": [{"Pounds": 26306.0, "ChemicalNumber": 222, "Chemical": "Dichloroethane, 1,2-", "Score": 17263.23, "CASStandard": "107-06-2"}, {"Pounds": 18.0, "ChemicalNumber": 135, "Chemical": "Chlorobenzene", "Score": 0.000443743, "CASStandard": "108-90-7"}, {"Pounds": 22.0, "ChemicalNumber": 63, "Chemical": "Bis(2-chloroethyl)ether", "Score": 181.899, "CASStandard": "111-44-4"}, {"Pounds": 21600.0, "ChemicalNumber": 491, "Chemical": "Propylene (Propene)", "Score": 0.147791, "CASStandard": "115-07-1"}, {"Pounds": 5.0, "ChemicalNumber": 145, "Chemical": "Chloroprene", "Score": 32.3055, "CASStandard": "126-99-8"}, {"Pounds": 5778.0, "ChemicalNumber": 531, "Chemical": "Tetrachloroethylene (Perchloroethylene)", "Score": 37.97585, "CASStandard": "127-18-4"}, {"Pounds": 190.0, "ChemicalNumber": 223, "Chemical": "Dichloroethylene, 1,2-", "Score": 0.1439891, "CASStandard": "540-59-0"}, {"Pounds": 86022.0, "ChemicalNumber": 115, "Chemical": "Carbon tetrachloride", "Score": 12608.65, "CASStandard": "56-23-5"}, {"Pounds": 3.0, "ChemicalNumber": 364, "Chemical": "Methanol", "Score": 3.79742e-06, "CASStandard": "67-56-1"}, {"Pounds": 453.0, "ChemicalNumber": 140, "Chemical": "Chloroform", "Score": 263.259, "CASStandard": "67-66-3"}, {"Pounds": 1.0, "ChemicalNumber": 323, "Chemical": "Hexachloroethane", "Score": 0.0993162, "CASStandard": "67-72-1"}, {"Pounds": 20.0, "ChemicalNumber": 51, "Chemical": "Benzene", "Score": 3.92802, "CASStandard": "71-43-2"}, {"Pounds": 17722.0, "ChemicalNumber": 291, "Chemical": "Ethylene", "Score": 0.0652699, "CASStandard": "74-85-1"}, {"Pounds": 110.0, "ChemicalNumber": 139, "Chemical": "Chloroethane (Ethyl chloride)", "Score": 0.000272142, "CASStandard": "75-00-3"}, {"Pounds": 148.0, "ChemicalNumber": 586, "Chemical": "Vinyl chloride", "Score": 30.54259, "CASStandard": "75-01-4"}, {"Pounds": 1.0, "ChemicalNumber": 587, "Chemical": "Vinylidene chloride", "Score": 0.000116015, "CASStandard": "75-35-4"}, {"Pounds": 6223.0, "ChemicalNumber": 331, "Chemical": "Hydrochloric acid", "Score": 7.781269999999999, "CASStandard": "7647-01-0"}, {"Pounds": 3215.0, "ChemicalNumber": 29, "Chemical": "Ammonia", "Score": 0.773125, "CASStandard": "7664-41-7"}, {"Pounds": 12470.0, "ChemicalNumber": 124, "Chemical": "Chlorine", "Score": 2007.7759999999998, "CASStandard": "7782-50-5"}, {"Pounds": 378.0, "ChemicalNumber": 566, "Chemical": "Trichloroethane, 1,1,2-", "Score": 15.250396, "CASStandard": "79-00-5"}, {"Pounds": 80.0, "ChemicalNumber": 567, "Chemical": "Trichloroethylene", "Score": 8.2945, "CASStandard": "79-01-6"}, {"Pounds": 61.0, "ChemicalNumber": 529, "Chemical": "Tetrachloroethane, 1,1,2,2-", "Score": 90.6629, "CASStandard": "79-34-5"}, {"Pounds": 1.0, "ChemicalNumber": 320, "Chemical": "Hexachloro-1,3-butadiene", "Score": 0.0560264, "CASStandard": "87-68-3"}]}, "1994": {"state_score_percentile": 84, "us_pounds_percentile": 90, "TotalPounds": 158507.0, "us_score_percentile": 88, "state_pounds_percentile": 87, "TotalScore": 27970.41880573513, "Submissions": [{"Pounds": 23520.0, "ChemicalNumber": 222, "Chemical": "Dichloroethane, 1,2-", "Score": 15623.98, "CASStandard": "107-06-2"}, {"Pounds": 18.0, "ChemicalNumber": 135, "Chemical": "Chlorobenzene", "Score": 0.000449434, "CASStandard": "108-90-7"}, {"Pounds": 22.0, "ChemicalNumber": 63, "Chemical": "Bis(2-chloroethyl)ether", "Score": 184.243, "CASStandard": "111-44-4"}, {"Pounds": 21600.0, "ChemicalNumber": 491, "Chemical": "Propylene (Propene)", "Score": 0.149772, "CASStandard": "115-07-1"}, {"Pounds": 5780.0, "ChemicalNumber": 531, "Chemical": "Tetrachloroethylene (Perchloroethylene)", "Score": 38.470729999999996, "CASStandard": "127-18-4"}, {"Pounds": 187.0, "ChemicalNumber": 223, "Chemical": "Dichloroethylene, 1,2-", "Score": 0.1435579, "CASStandard": "540-59-0"}, {"Pounds": 59700.0, "ChemicalNumber": 115, "Chemical": "Carbon tetrachloride", "Score": 8808.2, "CASStandard": "56-23-5"}, {"Pounds": 3.0, "ChemicalNumber": 364, "Chemical": "Methanol", "Score": 3.84613e-06, "CASStandard": "67-56-1"}, {"Pounds": 450.0, "ChemicalNumber": 140, "Chemical": "Chloroform", "Score": 264.864, "CASStandard": "67-66-3"}, {"Pounds": 1.0, "ChemicalNumber": 323, "Chemical": "Hexachloroethane", "Score": 0.100588, "CASStandard": "67-72-1"}, {"Pounds": 11500.0, "ChemicalNumber": 291, "Chemical": "Ethylene", "Score": 0.0429054, "CASStandard": "74-85-1"}, {"Pounds": 134.0, "ChemicalNumber": 139, "Chemical": "Chloroethane (Ethyl chloride)", "Score": 0.000333844, "CASStandard": "75-00-3"}, {"Pounds": 35.0, "ChemicalNumber": 586, "Chemical": "Vinyl chloride", "Score": 7.26661, "CASStandard": "75-01-4"}, {"Pounds": 1.0, "ChemicalNumber": 587, "Chemical": "Vinylidene chloride", "Score": 0.000117531, "CASStandard": "75-35-4"}, {"Pounds": 10000.0, "ChemicalNumber": 138, "Chemical": "Chlorodifluoromethane (HCFC-22)", "Score": 0.00502918, "CASStandard": "75-45-6"}, {"Pounds": 4117.0, "ChemicalNumber": 331, "Chemical": "Hydrochloric acid", "Score": 5.1474857, "CASStandard": "7647-01-0"}, {"Pounds": 3200.0, "ChemicalNumber": 29, "Chemical": "Ammonia", "Score": 0.777854, "CASStandard": "7664-41-7"}, {"Pounds": 45.0, "ChemicalNumber": 521, "Chemical": "Sulfuric acid", "Score": 1.12868, "CASStandard": "7664-93-9"}, {"Pounds": 17730.0, "ChemicalNumber": 124, "Chemical": "Chlorine", "Score": 2925.889, "CASStandard": "7782-50-5"}, {"Pounds": 375.0, "ChemicalNumber": 566, "Chemical": "Trichloroethane, 1,1,2-", "Score": 15.322715, "CASStandard": "79-00-5"}, {"Pounds": 27.0, "ChemicalNumber": 567, "Chemical": "Trichloroethylene", "Score": 2.80483, "CASStandard": "79-01-6"}, {"Pounds": 61.0, "ChemicalNumber": 529, "Chemical": "Tetrachloroethane, 1,1,2,2-", "Score": 91.8244, "CASStandard": "79-34-5"}, {"Pounds": 1.0, "ChemicalNumber": 320, "Chemical": "Hexachloro-1,3-butadiene", "Score": 0.0567439, "CASStandard": "87-68-3"}]}, "1995": {"state_score_percentile": 80, "us_pounds_percentile": 82, "TotalPounds": 72337.0, "us_score_percentile": 84, "state_pounds_percentile": 77, "TotalScore": 15769.074977218848, "Submissions": [{"Pounds": 17310.0, "ChemicalNumber": 222, "Chemical": "Dichloroethane, 1,2-", "Score": 11615.8, "CASStandard": "107-06-2"}, {"Pounds": 15.0, "ChemicalNumber": 135, "Chemical": "Chlorobenzene", "Score": 0.00037927, "CASStandard": "108-90-7"}, {"Pounds": 8.0, "ChemicalNumber": 63, "Chemical": "Bis(2-chloroethyl)ether", "Score": 67.8496, "CASStandard": "111-44-4"}, {"Pounds": 11300.0, "ChemicalNumber": 491, "Chemical": "Propylene (Propene)", "Score": 0.0793886, "CASStandard": "115-07-1"}, {"Pounds": 3370.0, "ChemicalNumber": 531, "Chemical": "Tetrachloroethylene (Perchloroethylene)", "Score": 22.710659999999997, "CASStandard": "127-18-4"}, {"Pounds": 144.0, "ChemicalNumber": 223, "Chemical": "Dichloroethylene, 1,2-", "Score": 0.1117588, "CASStandard": "540-59-0"}, {"Pounds": 18410.0, "ChemicalNumber": 115, "Chemical": "Carbon tetrachloride", "Score": 2797.5519999999997, "CASStandard": "56-23-5"}, {"Pounds": 3.0, "ChemicalNumber": 364, "Chemical": "Methanol", "Score": 3.89485e-06, "CASStandard": "67-56-1"}, {"Pounds": 335.0, "ChemicalNumber": 140, "Chemical": "Chloroform", "Score": 199.67, "CASStandard": "67-66-3"}, {"Pounds": 1.0, "ChemicalNumber": 323, "Chemical": "Hexachloroethane", "Score": 0.10186, "CASStandard": "67-72-1"}, {"Pounds": 7120.0, "ChemicalNumber": 291, "Chemical": "Ethylene", "Score": 0.0269052, "CASStandard": "74-85-1"}, {"Pounds": 67.0, "ChemicalNumber": 139, "Chemical": "Chloroethane (Ethyl chloride)", "Score": 0.000170008, "CASStandard": "75-00-3"}, {"Pounds": 130.0, "ChemicalNumber": 586, "Chemical": "Vinyl chloride", "Score": 27.2436, "CASStandard": "75-01-4"}, {"Pounds": 1.0, "ChemicalNumber": 587, "Chemical": "Vinylidene chloride", "Score": 0.000119046, "CASStandard": "75-35-4"}, {"Pounds": 4200.0, "ChemicalNumber": 331, "Chemical": "Hydrochloric acid", "Score": 5.30679, "CASStandard": "7647-01-0"}, {"Pounds": 3855.0, "ChemicalNumber": 29, "Chemical": "Ammonia", "Score": 0.952851, "CASStandard": "7664-41-7"}, {"Pounds": 5800.0, "ChemicalNumber": 124, "Chemical": "Chlorine", "Score": 966.453, "CASStandard": "7782-50-5"}, {"Pounds": 220.0, "ChemicalNumber": 566, "Chemical": "Trichloroethane, 1,1,2-", "Score": 9.10697, "CASStandard": "79-00-5"}, {"Pounds": 11.0, "ChemicalNumber": 567, "Chemical": "Trichloroethylene", "Score": 1.17456, "CASStandard": "79-01-6"}, {"Pounds": 36.0, "ChemicalNumber": 529, "Chemical": "Tetrachloroethane, 1,1,2,2-", "Score": 54.8769, "CASStandard": "79-34-5"}, {"Pounds": 1.0, "ChemicalNumber": 320, "Chemical": "Hexachloro-1,3-butadiene", "Score": 0.0574614, "CASStandard": "87-68-3"}]}, "1996": {"state_score_percentile": 80, "us_pounds_percentile": 80, "TotalPounds": 62598.0, "us_score_percentile": 84, "state_pounds_percentile": 77, "TotalScore": 14912.60958216456, "Submissions": [{"Pounds": 18100.0, "ChemicalNumber": 222, "Chemical": "Dichloroethane, 1,2-", "Score": 12149.32, "CASStandard": "107-06-2"}, {"Pounds": 4.0, "ChemicalNumber": 135, "Chemical": "Chlorobenzene", "Score": 0.000102403, "CASStandard": "108-90-7"}, {"Pounds": 24.0, "ChemicalNumber": 63, "Chemical": "Bis(2-chloroethyl)ether", "Score": 206.105, "CASStandard": "111-44-4"}, {"Pounds": 1020.0, "ChemicalNumber": 491, "Chemical": "Propylene (Propene)", "Score": 0.00725956, "CASStandard": "115-07-1"}, {"Pounds": 14.0, "ChemicalNumber": 531, "Chemical": "Tetrachloroethylene (Perchloroethylene)", "Score": 0.0947652, "CASStandard": "127-18-4"}, {"Pounds": 95.0, "ChemicalNumber": 223, "Chemical": "Dichloroethylene, 1,2-", "Score": 0.07448350000000001, "CASStandard": "540-59-0"}, {"Pounds": 8137.0, "ChemicalNumber": 115, "Chemical": "Carbon tetrachloride", "Score": 1258.72281, "CASStandard": "56-23-5"}, {"Pounds": 3.0, "ChemicalNumber": 364, "Chemical": "Methanol", "Score": 3.94356e-06, "CASStandard": "67-56-1"}, {"Pounds": 200.0, "ChemicalNumber": 140, "Chemical": "Chloroform", "Score": 120.695, "CASStandard": "67-66-3"}, {"Pounds": 1.0, "ChemicalNumber": 323, "Chemical": "Hexachloroethane", "Score": 0.103131, "CASStandard": "67-72-1"}, {"Pounds": 5200.0, "ChemicalNumber": 291, "Chemical": "Ethylene", "Score": 0.019899, "CASStandard": "74-85-1"}, {"Pounds": 220.0, "ChemicalNumber": 139, "Chemical": "Chloroethane (Ethyl chloride)", "Score": 0.0005496559999999999, "CASStandard": "75-00-3"}, {"Pounds": 1030.0, "ChemicalNumber": 586, "Chemical": "Vinyl chloride", "Score": 220.801, "CASStandard": "75-01-4"}, {"Pounds": 1.0, "ChemicalNumber": 587, "Chemical": "Vinylidene chloride", "Score": 0.000120562, "CASStandard": "75-35-4"}, {"Pounds": 18000.0, "ChemicalNumber": 138, "Chemical": "Chlorodifluoromethane (HCFC-22)", "Score": 0.00928144, "CASStandard": "75-45-6"}, {"Pounds": 4300.0, "ChemicalNumber": 331, "Chemical": "Hydrochloric acid", "Score": 5.495657, "CASStandard": "7647-01-0"}, {"Pounds": 640.0, "ChemicalNumber": 29, "Chemical": "Ammonia", "Score": 0.16501, "CASStandard": "7664-41-7"}, {"Pounds": 5485.0, "ChemicalNumber": 124, "Chemical": "Chlorine", "Score": 927.036, "CASStandard": "7782-50-5"}, {"Pounds": 100.0, "ChemicalNumber": 566, "Chemical": "Trichloroethane, 1,1,2-", "Score": 4.19124, "CASStandard": "79-00-5"}, {"Pounds": 11.0, "ChemicalNumber": 567, "Chemical": "Trichloroethylene", "Score": 1.18929, "CASStandard": "79-01-6"}, {"Pounds": 12.0, "ChemicalNumber": 529, "Chemical": "Tetrachloroethane, 1,1,2,2-", "Score": 18.5208, "CASStandard": "79-34-5"}, {"Pounds": 1.0, "ChemicalNumber": 320, "Chemical": "Hexachloro-1,3-butadiene", "Score": 0.0581789, "CASStandard": "87-68-3"}]}, "1997": {"state_score_percentile": 79, "us_pounds_percentile": 80, "TotalPounds": 59202.0, "us_score_percentile": 84, "state_pounds_percentile": 76, "TotalScore": 13404.881460053168, "Submissions": [{"Pounds": 15225.0, "ChemicalNumber": 222, "Chemical": "Dichloroethane, 1,2-", "Score": 10456.17, "CASStandard": "107-06-2"}, {"Pounds": 5.0, "ChemicalNumber": 135, "Chemical": "Chlorobenzene", "Score": 0.000129585, "CASStandard": "108-90-7"}, {"Pounds": 12.0, "ChemicalNumber": 63, "Chemical": "Bis(2-chloroethyl)ether", "Score": 104.331, "CASStandard": "111-44-4"}, {"Pounds": 1830.0, "ChemicalNumber": 491, "Chemical": "Propylene (Propene)", "Score": 0.0131923, "CASStandard": "115-07-1"}, {"Pounds": 5.0, "ChemicalNumber": 145, "Chemical": "Chloroprene", "Score": 34.0265, "CASStandard": "126-99-8"}, {"Pounds": 57.0, "ChemicalNumber": 531, "Chemical": "Tetrachloroethylene (Perchloroethylene)", "Score": 0.3928449, "CASStandard": "127-18-4"}, {"Pounds": 71.0, "ChemicalNumber": 223, "Chemical": "Dichloroethylene, 1,2-", "Score": 0.055815000000000003, "CASStandard": "540-59-0"}, {"Pounds": 8111.0, "ChemicalNumber": 115, "Chemical": "Carbon tetrachloride", "Score": 1270.14589, "CASStandard": "56-23-5"}, {"Pounds": 3.0, "ChemicalNumber": 364, "Chemical": "Methanol", "Score": 3.99227e-06, "CASStandard": "67-56-1"}, {"Pounds": 260.0, "ChemicalNumber": 140, "Chemical": "Chloroform", "Score": 158.838, "CASStandard": "67-66-3"}, {"Pounds": 1.0, "ChemicalNumber": 323, "Chemical": "Hexachloroethane", "Score": 0.104403, "CASStandard": "67-72-1"}, {"Pounds": 5.0, "ChemicalNumber": 51, "Chemical": "Benzene", "Score": 1.03242, "CASStandard": "71-43-2"}, {"Pounds": 6222.0, "ChemicalNumber": 291, "Chemical": "Ethylene", "Score": 0.0241071464, "CASStandard": "74-85-1"}, {"Pounds": 75.0, "ChemicalNumber": 139, "Chemical": "Chloroethane (Ethyl chloride)", "Score": 0.0001892315, "CASStandard": "75-00-3"}, {"Pounds": 1620.0, "ChemicalNumber": 586, "Chemical": "Vinyl chloride", "Score": 351.8179, "CASStandard": "75-01-4"}, {"Pounds": 1.0, "ChemicalNumber": 587, "Chemical": "Vinylidene chloride", "Score": 0.000122078, "CASStandard": "75-35-4"}, {"Pounds": 14000.0, "ChemicalNumber": 138, "Chemical": "Chlorodifluoromethane (HCFC-22)", "Score": 0.00730792, "CASStandard": "75-45-6"}, {"Pounds": 4290.0, "ChemicalNumber": 331, "Chemical": "Hydrochloric acid", "Score": 5.5385795, "CASStandard": "7647-01-0"}, {"Pounds": 1370.0, "ChemicalNumber": 29, "Chemical": "Ammonia", "Score": 0.357581, "CASStandard": "7664-41-7"}, {"Pounds": 5785.0, "ChemicalNumber": 124, "Chemical": "Chlorine", "Score": 989.0167, "CASStandard": "7782-50-5"}, {"Pounds": 225.0, "ChemicalNumber": 566, "Chemical": "Trichloroethane, 1,1,2-", "Score": 9.54661, "CASStandard": "79-00-5"}, {"Pounds": 14.0, "ChemicalNumber": 567, "Chemical": "Trichloroethylene", "Score": 1.529068, "CASStandard": "79-01-6"}, {"Pounds": 14.0, "ChemicalNumber": 529, "Chemical": "Tetrachloroethane, 1,1,2,2-", "Score": 21.8742, "CASStandard": "79-34-5"}, {"Pounds": 1.0, "ChemicalNumber": 320, "Chemical": "Hexachloro-1,3-butadiene", "Score": 0.0588964, "CASStandard": "87-68-3"}]}, "1998": {"state_score_percentile": 83, "us_pounds_percentile": 82, "TotalPounds": 70535.0, "us_score_percentile": 86, "state_pounds_percentile": 78, "TotalScore": 17914.54619854554, "Submissions": [{"Pounds": 20820.0, "ChemicalNumber": 222, "Chemical": "Dichloroethane, 1,2-", "Score": 14407.66, "CASStandard": "107-06-2"}, {"Pounds": 4.0, "ChemicalNumber": 63, "Chemical": "Bis(2-chloroethyl)ether", "Score": 35.2031, "CASStandard": "111-44-4"}, {"Pounds": 1905.0, "ChemicalNumber": 491, "Chemical": "Propylene (Propene)", "Score": 0.013915614, "CASStandard": "115-07-1"}, {"Pounds": 34.0, "ChemicalNumber": 531, "Chemical": "Tetrachloroethylene (Perchloroethylene)", "Score": 0.2346677, "CASStandard": "127-18-4"}, {"Pounds": 93.0, "ChemicalNumber": 223, "Chemical": "Dichloroethylene, 1,2-", "Score": 0.0741162, "CASStandard": "540-59-0"}, {"Pounds": 8120.0, "ChemicalNumber": 115, "Chemical": "Carbon tetrachloride", "Score": 1287.03308, "CASStandard": "56-23-5"}, {"Pounds": 246.0, "ChemicalNumber": 140, "Chemical": "Chloroform", "Score": 152.116, "CASStandard": "67-66-3"}, {"Pounds": 1.0, "ChemicalNumber": 323, "Chemical": "Hexachloroethane", "Score": 0.105675, "CASStandard": "67-72-1"}, {"Pounds": 5.0, "ChemicalNumber": 51, "Chemical": "Benzene", "Score": 1.04503, "CASStandard": "71-43-2"}, {"Pounds": 7799.0, "ChemicalNumber": 291, "Chemical": "Ethylene", "Score": 0.03057625, "CASStandard": "74-85-1"}, {"Pounds": 61.0, "ChemicalNumber": 139, "Chemical": "Chloroethane (Ethyl chloride)", "Score": 0.00015441154, "CASStandard": "75-00-3"}, {"Pounds": 3854.0, "ChemicalNumber": 586, "Chemical": "Vinyl chloride", "Score": 847.3098, "CASStandard": "75-01-4"}, {"Pounds": 15500.0, "ChemicalNumber": 138, "Chemical": "Chlorodifluoromethane (HCFC-22)", "Score": 0.00818947, "CASStandard": "75-45-6"}, {"Pounds": 3207.0, "ChemicalNumber": 331, "Chemical": "Hydrochloric acid", "Score": 4.185238, "CASStandard": "7647-01-0"}, {"Pounds": 2040.0, "ChemicalNumber": 29, "Chemical": "Ammonia", "Score": 0.533598, "CASStandard": "7664-41-7"}, {"Pounds": 6727.0, "ChemicalNumber": 124, "Chemical": "Chlorine", "Score": 1156.867, "CASStandard": "7782-50-5"}, {"Pounds": 104.0, "ChemicalNumber": 566, "Chemical": "Trichloroethane, 1,1,2-", "Score": 4.46643, "CASStandard": "79-00-5"}, {"Pounds": 3.0, "ChemicalNumber": 567, "Chemical": "Trichloroethylene", "Score": 0.328824, "CASStandard": "79-01-6"}, {"Pounds": 11.0, "ChemicalNumber": 529, "Chemical": "Tetrachloroethane, 1,1,2,2-", "Score": 17.27119, "CASStandard": "79-34-5"}, {"Pounds": 1.0, "ChemicalNumber": 320, "Chemical": "Hexachloro-1,3-butadiene", "Score": 0.0596139, "CASStandard": "87-68-3"}]}, "1999": {"state_score_percentile": 83, "us_pounds_percentile": 79, "TotalPounds": 53633.0, "us_score_percentile": 86, "state_pounds_percentile": 75, "TotalScore": 16899.040634989004, "Submissions": [{"Pounds": 19608.0, "ChemicalNumber": 222, "Chemical": "Dichloroethane, 1,2-", "Score": 13767.259999999998, "CASStandard": "107-06-2"}, {"Pounds": 7.0, "ChemicalNumber": 63, "Chemical": "Bis(2-chloroethyl)ether", "Score": 62.351, "CASStandard": "111-44-4"}, {"Pounds": 1931.0, "ChemicalNumber": 491, "Chemical": "Propylene (Propene)", "Score": 0.014279866, "CASStandard": "115-07-1"}, {"Pounds": 5.0, "ChemicalNumber": 145, "Chemical": "Chloroprene", "Score": 34.887, "CASStandard": "126-99-8"}, {"Pounds": 31.0, "ChemicalNumber": 531, "Chemical": "Tetrachloroethylene (Perchloroethylene)", "Score": 0.21547, "CASStandard": "127-18-4"}, {"Pounds": 69.0, "ChemicalNumber": 223, "Chemical": "Dichloroethylene, 1,2-", "Score": 0.054983729999999995, "CASStandard": "540-59-0"}, {"Pounds": 8125.0, "ChemicalNumber": 115, "Chemical": "Carbon tetrachloride", "Score": 1303.31394, "CASStandard": "56-23-5"}, {"Pounds": 167.0, "ChemicalNumber": 140, "Chemical": "Chloroform", "Score": 104.509, "CASStandard": "67-66-3"}, {"Pounds": 1.0, "ChemicalNumber": 323, "Chemical": "Hexachloroethane", "Score": 0.106947, "CASStandard": "67-72-1"}, {"Pounds": 5.0, "ChemicalNumber": 51, "Chemical": "Benzene", "Score": 1.05763, "CASStandard": "71-43-2"}, {"Pounds": 9535.0, "ChemicalNumber": 291, "Chemical": "Ethylene", "Score": 0.03776728, "CASStandard": "74-85-1"}, {"Pounds": 159.0, "ChemicalNumber": 139, "Chemical": "Chloroethane (Ethyl chloride)", "Score": 0.000414603, "CASStandard": "75-00-3"}, {"Pounds": 2274.0, "ChemicalNumber": 586, "Chemical": "Vinyl chloride", "Score": 503.058, "CASStandard": "75-01-4"}, {"Pounds": 1.0, "ChemicalNumber": 587, "Chemical": "Vinylidene chloride", "Score": 0.00012511, "CASStandard": "75-35-4"}, {"Pounds": 3212.0, "ChemicalNumber": 331, "Chemical": "Hydrochloric acid", "Score": 4.235312, "CASStandard": "7647-01-0"}, {"Pounds": 2099.0, "ChemicalNumber": 29, "Chemical": "Ammonia", "Score": 0.5549189999999999, "CASStandard": "7664-41-7"}, {"Pounds": 6281.0, "ChemicalNumber": 124, "Chemical": "Chlorine", "Score": 1095.981, "CASStandard": "7782-50-5"}, {"Pounds": 105.0, "ChemicalNumber": 566, "Chemical": "Trichloroethane, 1,1,2-", "Score": 4.56366, "CASStandard": "79-00-5"}, {"Pounds": 7.0, "ChemicalNumber": 567, "Chemical": "Trichloroethylene", "Score": 0.773555, "CASStandard": "79-01-6"}, {"Pounds": 10.0, "ChemicalNumber": 529, "Chemical": "Tetrachloroethane, 1,1,2,2-", "Score": 16.0053, "CASStandard": "79-34-5"}, {"Pounds": 1.0, "ChemicalNumber": 320, "Chemical": "Hexachloro-1,3-butadiene", "Score": 0.0603314, "CASStandard": "87-68-3"}]}, "2000": {"state_score_percentile": 83, "us_pounds_percentile": 84, "TotalPounds": 73360.219838, "us_score_percentile": 86, "state_pounds_percentile": 81, "TotalScore": 18738.2231563559, "Submissions": [{"Pounds": 20370.0, "ChemicalNumber": 222, "Chemical": "Dichloroethane, 1,2-", "Score": 14567.982, "CASStandard": "107-06-2"}, {"Pounds": 8.0, "ChemicalNumber": 135, "Chemical": "Chlorobenzene", "Score": 0.0002116135, "CASStandard": "108-90-7"}, {"Pounds": 19.0, "ChemicalNumber": 63, "Chemical": "Bis(2-chloroethyl)ether", "Score": 168.8943, "CASStandard": "111-44-4"}, {"Pounds": 1866.0, "ChemicalNumber": 491, "Chemical": "Propylene (Propene)", "Score": 0.013966948600000001, "CASStandard": "115-07-1"}, {"Pounds": 1.0, "ChemicalNumber": 321, "Chemical": "Hexachlorobenzene", "Score": 12.3655, "CASStandard": "118-74-1"}, {"Pounds": 5.0, "ChemicalNumber": 145, "Chemical": "Chloroprene", "Score": 35.3173, "CASStandard": "126-99-8"}, {"Pounds": 34.0, "ChemicalNumber": 531, "Chemical": "Tetrachloroethylene (Perchloroethylene)", "Score": 0.2400102, "CASStandard": "127-18-4"}, {"Pounds": 78.0, "ChemicalNumber": 223, "Chemical": "Dichloroethylene, 1,2-", "Score": 0.0634888, "CASStandard": "540-59-0"}, {"Pounds": 1.0, "ChemicalNumber": 216, "Chemical": "Dichlorobenzene, 1,3-", "Score": 0.000138227, "CASStandard": "541-73-1"}, {"Pounds": 8395.0, "ChemicalNumber": 115, "Chemical": "Carbon tetrachloride", "Score": 1362.64747, "CASStandard": "56-23-5"}, {"Pounds": 387.0, "ChemicalNumber": 140, "Chemical": "Chloroform", "Score": 243.1978, "CASStandard": "67-66-3"}, {"Pounds": 5.0, "ChemicalNumber": 51, "Chemical": "Benzene", "Score": 1.07024, "CASStandard": "71-43-2"}, {"Pounds": 7912.0, "ChemicalNumber": 291, "Chemical": "Ethylene", "Score": 0.031775450000000004, "CASStandard": "74-85-1"}, {"Pounds": 5.0, "ChemicalNumber": 141, "Chemical": "Chloromethane", "Score": 0.0247247, "CASStandard": "74-87-3"}, {"Pounds": 129.0, "ChemicalNumber": 156, "Chemical": "Copper and copper compounds", "Score": 1.35795, "CASStandard": "7440-50-8"}, {"Pounds": 222.0, "ChemicalNumber": 139, "Chemical": "Chloroethane (Ethyl chloride)", "Score": 0.0005759888, "CASStandard": "75-00-3"}, {"Pounds": 2005.0, "ChemicalNumber": 586, "Chemical": "Vinyl chloride", "Score": 450.4178, "CASStandard": "75-01-4"}, {"Pounds": 2.0, "ChemicalNumber": 587, "Chemical": "Vinylidene chloride", "Score": 0.000252158, "CASStandard": "75-35-4"}, {"Pounds": 17041.0, "ChemicalNumber": 138, "Chemical": "Chlorodifluoromethane (HCFC-22)", "Score": 0.00922038, "CASStandard": "75-45-6"}, {"Pounds": 464.0, "ChemicalNumber": 331, "Chemical": "Hydrochloric acid", "Score": 0.61766089, "CASStandard": "7647-01-0"}, {"Pounds": 1769.0, "ChemicalNumber": 29, "Chemical": "Ammonia", "Score": 0.472807, "CASStandard": "7664-41-7"}, {"Pounds": 6646.0, "ChemicalNumber": 124, "Chemical": "Chlorine", "Score": 1169.6970000000001, "CASStandard": "7782-50-5"}, {"Pounds": 167.0, "ChemicalNumber": 566, "Chemical": "Trichloroethane, 1,1,2-", "Score": 7.19512, "CASStandard": "79-00-5"}, {"Pounds": 5792.0, "ChemicalNumber": 567, "Chemical": "Trichloroethylene", "Score": 657.2374440000001, "CASStandard": "79-01-6"}, {"Pounds": 37.0, "ChemicalNumber": 529, "Chemical": "Tetrachloroethane, 1,1,2,2-", "Score": 59.368399999999994, "CASStandard": "79-34-5"}, {"Pounds": 0.219838, "ChemicalNumber": 614, "Chemical": "Dioxin and dioxin-like compounds", "Score": 0.0, "CASStandard": "N150"}]}, "2001": {"state_score_percentile": 80, "us_pounds_percentile": 84, "TotalPounds": 60208.208152, "us_score_percentile": 84, "state_pounds_percentile": 81, "TotalScore": 8200.0028372959, "Submissions": [{"Pounds": 8060.0, "ChemicalNumber": 222, "Chemical": "Dichloroethane, 1,2-", "Score": 5765.727999999999, "CASStandard": "107-06-2"}, {"Pounds": 9.0, "ChemicalNumber": 135, "Chemical": "Chlorobenzene", "Score": 0.000237076, "CASStandard": "108-90-7"}, {"Pounds": 18.0, "ChemicalNumber": 63, "Chemical": "Bis(2-chloroethyl)ether", "Score": 161.396, "CASStandard": "111-44-4"}, {"Pounds": 618.0, "ChemicalNumber": 491, "Chemical": "Propylene (Propene)", "Score": 0.0046483033, "CASStandard": "115-07-1"}, {"Pounds": 14.0, "ChemicalNumber": 531, "Chemical": "Tetrachloroethylene (Perchloroethylene)", "Score": 0.09736779999999999, "CASStandard": "127-18-4"}, {"Pounds": 62.0, "ChemicalNumber": 223, "Chemical": "Dichloroethylene, 1,2-", "Score": 0.050241299999999996, "CASStandard": "540-59-0"}, {"Pounds": 112.0, "ChemicalNumber": 115, "Chemical": "Carbon tetrachloride", "Score": 18.17121, "CASStandard": "56-23-5"}, {"Pounds": 227.0, "ChemicalNumber": 140, "Chemical": "Chloroform", "Score": 142.4549, "CASStandard": "67-66-3"}, {"Pounds": 1661.0, "ChemicalNumber": 291, "Chemical": "Ethylene", "Score": 0.00668356, "CASStandard": "74-85-1"}, {"Pounds": 18.0, "ChemicalNumber": 346, "Chemical": "Lead and lead compounds", "Score": 3.06808, "CASStandard": "7439-92-1"}, {"Pounds": 146.0, "ChemicalNumber": 139, "Chemical": "Chloroethane (Ethyl chloride)", "Score": 0.00037861460000000003, "CASStandard": "75-00-3"}, {"Pounds": 2075.0, "ChemicalNumber": 586, "Chemical": "Vinyl chloride", "Score": 468.6315, "CASStandard": "75-01-4"}, {"Pounds": 2.0, "ChemicalNumber": 587, "Chemical": "Vinylidene chloride", "Score": 0.000253042, "CASStandard": "75-35-4"}, {"Pounds": 28755.0, "ChemicalNumber": 138, "Chemical": "Chlorodifluoromethane (HCFC-22)", "Score": 0.0156267, "CASStandard": "75-45-6"}, {"Pounds": 5908.0, "ChemicalNumber": 331, "Chemical": "Hydrochloric acid", "Score": 7.8948, "CASStandard": "7647-01-0"}, {"Pounds": 1461.0, "ChemicalNumber": 29, "Chemical": "Ammonia", "Score": 0.3932809, "CASStandard": "7664-41-7"}, {"Pounds": 5867.0, "ChemicalNumber": 124, "Chemical": "Chlorine", "Score": 1035.643, "CASStandard": "7782-50-5"}, {"Pounds": 165.0, "ChemicalNumber": 566, "Chemical": "Trichloroethane, 1,1,2-", "Score": 7.10463, "CASStandard": "79-00-5"}, {"Pounds": 5019.0, "ChemicalNumber": 567, "Chemical": "Trichloroethylene", "Score": 572.029, "CASStandard": "79-01-6"}, {"Pounds": 11.0, "ChemicalNumber": 529, "Chemical": "Tetrachloroethane, 1,1,2,2-", "Score": 17.313, "CASStandard": "79-34-5"}, {"Pounds": 0.208152, "ChemicalNumber": 614, "Chemical": "Dioxin and dioxin-like compounds", "Score": 0.0, "CASStandard": "N150"}]}, "2002": {"state_score_percentile": 81, "us_pounds_percentile": 76, "TotalPounds": 27118.0663705, "us_score_percentile": 85, "state_pounds_percentile": 71, "TotalScore": 8086.630529548851, "Submissions": [{"Pounds": 7888.0, "ChemicalNumber": 222, "Chemical": "Dichloroethane, 1,2-", "Score": 5693.931, "CASStandard": "107-06-2"}, {"Pounds": 16.0, "ChemicalNumber": 135, "Chemical": "Chlorobenzene", "Score": 0.000427587, "CASStandard": "108-90-7"}, {"Pounds": 19.0, "ChemicalNumber": 63, "Chemical": "Bis(2-chloroethyl)ether", "Score": 171.4475, "CASStandard": "111-44-4"}, {"Pounds": 1111.0, "ChemicalNumber": 491, "Chemical": "Propylene (Propene)", "Score": 0.00839175975, "CASStandard": "115-07-1"}, {"Pounds": 1.2, "ChemicalNumber": 321, "Chemical": "Hexachlorobenzene", "Score": 14.264, "CASStandard": "118-74-1"}, {"Pounds": 14.0, "ChemicalNumber": 531, "Chemical": "Tetrachloroethylene (Perchloroethylene)", "Score": 0.0979945, "CASStandard": "127-18-4"}, {"Pounds": 51.0, "ChemicalNumber": 223, "Chemical": "Dichloroethylene, 1,2-", "Score": 0.041562100000000005, "CASStandard": "540-59-0"}, {"Pounds": 214.0, "ChemicalNumber": 115, "Chemical": "Carbon tetrachloride", "Score": 34.95729, "CASStandard": "56-23-5"}, {"Pounds": 218.0, "ChemicalNumber": 140, "Chemical": "Chloroform", "Score": 137.6138, "CASStandard": "67-66-3"}, {"Pounds": 2253.0, "ChemicalNumber": 291, "Chemical": "Ethylene", "Score": 0.00908718, "CASStandard": "74-85-1"}, {"Pounds": 7.8, "ChemicalNumber": 346, "Chemical": "Lead and lead compounds", "Score": 1.33292, "CASStandard": "7439-92-1"}, {"Pounds": 75.0, "ChemicalNumber": 139, "Chemical": "Chloroethane (Ethyl chloride)", "Score": 0.0001954971, "CASStandard": "75-00-3"}, {"Pounds": 3144.0, "ChemicalNumber": 586, "Chemical": "Vinyl chloride", "Score": 714.7227, "CASStandard": "75-01-4"}, {"Pounds": 2.0, "ChemicalNumber": 587, "Chemical": "Vinylidene chloride", "Score": 0.000253925, "CASStandard": "75-35-4"}, {"Pounds": 1485.0, "ChemicalNumber": 331, "Chemical": "Hydrochloric acid", "Score": 2.021823, "CASStandard": "7647-01-0"}, {"Pounds": 2659.0, "ChemicalNumber": 29, "Chemical": "Ammonia", "Score": 0.706394, "CASStandard": "7664-41-7"}, {"Pounds": 6396.0, "ChemicalNumber": 124, "Chemical": "Chlorine", "Score": 1128.376, "CASStandard": "7782-50-5"}, {"Pounds": 195.0, "ChemicalNumber": 566, "Chemical": "Trichloroethane, 1,1,2-", "Score": 8.43073, "CASStandard": "79-00-5"}, {"Pounds": 1354.0, "ChemicalNumber": 567, "Chemical": "Trichloroethylene", "Score": 154.994, "CASStandard": "79-01-6"}, {"Pounds": 15.0, "ChemicalNumber": 529, "Chemical": "Tetrachloroethane, 1,1,2,2-", "Score": 23.674459999999996, "CASStandard": "79-34-5"}, {"Pounds": 0.0663705, "ChemicalNumber": 614, "Chemical": "Dioxin and dioxin-like compounds", "Score": 0.0, "CASStandard": "N150"}]}, "2003": {"state_score_percentile": 81, "us_pounds_percentile": 80, "TotalPounds": 36447.90026459999, "us_score_percentile": 85, "state_pounds_percentile": 76, "TotalScore": 8178.378693664297, "Submissions": [{"Pounds": 8610.0, "ChemicalNumber": 222, "Chemical": "Dichloroethane, 1,2-", "Score": 6156.44, "CASStandard": "107-06-2"}, {"Pounds": 10.0, "ChemicalNumber": 135, "Chemical": "Chlorobenzene", "Score": 0.0002684177, "CASStandard": "108-90-7"}, {"Pounds": 16.0, "ChemicalNumber": 63, "Chemical": "Bis(2-chloroethyl)ether", "Score": 145.4291, "CASStandard": "111-44-4"}, {"Pounds": 1626.0, "ChemicalNumber": 491, "Chemical": "Propylene (Propene)", "Score": 0.01234633, "CASStandard": "115-07-1"}, {"Pounds": 0.1, "ChemicalNumber": 321, "Chemical": "Hexachlorobenzene", "Score": 1.25281, "CASStandard": "118-74-1"}, {"Pounds": 11.0, "ChemicalNumber": 531, "Chemical": "Tetrachloroethylene (Perchloroethylene)", "Score": 0.0775348, "CASStandard": "127-18-4"}, {"Pounds": 51.0, "ChemicalNumber": 223, "Chemical": "Dichloroethylene, 1,2-", "Score": 0.0416576, "CASStandard": "540-59-0"}, {"Pounds": 1.0, "ChemicalNumber": 216, "Chemical": "Dichlorobenzene, 1,3-", "Score": 0.000140046, "CASStandard": "541-73-1"}, {"Pounds": 21.0, "ChemicalNumber": 115, "Chemical": "Carbon tetrachloride", "Score": 3.37333, "CASStandard": "56-23-5"}, {"Pounds": 192.0, "ChemicalNumber": 140, "Chemical": "Chloroform", "Score": 121.7197, "CASStandard": "67-66-3"}, {"Pounds": 14080.0, "ChemicalNumber": 291, "Chemical": "Ethylene", "Score": 0.0572125, "CASStandard": "74-85-1"}, {"Pounds": 7.8, "ChemicalNumber": 346, "Chemical": "Lead and lead compounds", "Score": 1.33635, "CASStandard": "7439-92-1"}, {"Pounds": 85.0, "ChemicalNumber": 139, "Chemical": "Chloroethane (Ethyl chloride)", "Score": 0.0002216606, "CASStandard": "75-00-3"}, {"Pounds": 2664.0, "ChemicalNumber": 586, "Chemical": "Vinyl chloride", "Score": 608.0890999999999, "CASStandard": "75-01-4"}, {"Pounds": 2.0, "ChemicalNumber": 587, "Chemical": "Vinylidene chloride", "Score": 0.00025481, "CASStandard": "75-35-4"}, {"Pounds": 1303.0, "ChemicalNumber": 331, "Chemical": "Hydrochloric acid", "Score": 1.791772, "CASStandard": "7647-01-0"}, {"Pounds": 1309.0, "ChemicalNumber": 29, "Chemical": "Ammonia", "Score": 0.3568055, "CASStandard": "7664-41-7"}, {"Pounds": 6235.0, "ChemicalNumber": 124, "Chemical": "Chlorine", "Score": 1105.877, "CASStandard": "7782-50-5"}, {"Pounds": 111.0, "ChemicalNumber": 566, "Chemical": "Trichloroethane, 1,1,2-", "Score": 4.8237000000000005, "CASStandard": "79-00-5"}, {"Pounds": 103.0, "ChemicalNumber": 567, "Chemical": "Trichloroethylene", "Score": 11.8419, "CASStandard": "79-01-6"}, {"Pounds": 10.0, "ChemicalNumber": 529, "Chemical": "Tetrachloroethane, 1,1,2,2-", "Score": 15.85749, "CASStandard": "79-34-5"}, {"Pounds": 0.0002646, "ChemicalNumber": 614, "Chemical": "Dioxin and dioxin-like compounds", "Score": 0.0, "CASStandard": "N150"}]}, "2004": {"state_score_percentile": 77, "us_pounds_percentile": 75, "TotalPounds": 21191.300220499998, "us_score_percentile": 81, "state_pounds_percentile": 70, "TotalScore": 4072.7012156853907, "Submissions": [{"Pounds": 3229.0, "ChemicalNumber": 222, "Chemical": "Dichloroethane, 1,2-", "Score": 2343.9900000000002, "CASStandard": "107-06-2"}, {"Pounds": 5.0, "ChemicalNumber": 135, "Chemical": "Chlorobenzene", "Score": 0.0001327576, "CASStandard": "108-90-7"}, {"Pounds": 3.0, "ChemicalNumber": 63, "Chemical": "Bis(2-chloroethyl)ether", "Score": 26.4223, "CASStandard": "111-44-4"}, {"Pounds": 1165.0, "ChemicalNumber": 491, "Chemical": "Propylene (Propene)", "Score": 0.008881012099999998, "CASStandard": "115-07-1"}, {"Pounds": 8.0, "ChemicalNumber": 531, "Chemical": "Tetrachloroethylene (Perchloroethylene)", "Score": 0.05587452, "CASStandard": "127-18-4"}, {"Pounds": 42.0, "ChemicalNumber": 223, "Chemical": "Dichloroethylene, 1,2-", "Score": 0.03414703, "CASStandard": "540-59-0"}, {"Pounds": 13.0, "ChemicalNumber": 115, "Chemical": "Carbon tetrachloride", "Score": 2.0637939999999997, "CASStandard": "56-23-5"}, {"Pounds": 73.0, "ChemicalNumber": 140, "Chemical": "Chloroform", "Score": 46.2295, "CASStandard": "67-66-3"}, {"Pounds": 3031.0, "ChemicalNumber": 291, "Chemical": "Ethylene", "Score": 0.012390192999999999, "CASStandard": "74-85-1"}, {"Pounds": 8.3, "ChemicalNumber": 346, "Chemical": "Lead and lead compounds", "Score": 1.42566, "CASStandard": "7439-92-1"}, {"Pounds": 79.0, "ChemicalNumber": 139, "Chemical": "Chloroethane (Ethyl chloride)", "Score": 0.00020646268999999998, "CASStandard": "75-00-3"}, {"Pounds": 1118.0, "ChemicalNumber": 586, "Chemical": "Vinyl chloride", "Score": 256.35985999999997, "CASStandard": "75-01-4"}, {"Pounds": 1.0, "ChemicalNumber": 587, "Chemical": "Vinylidene chloride", "Score": 0.00012681, "CASStandard": "75-35-4"}, {"Pounds": 3329.0, "ChemicalNumber": 331, "Chemical": "Hydrochloric acid", "Score": 4.667899, "CASStandard": "7647-01-0"}, {"Pounds": 1332.0, "ChemicalNumber": 29, "Chemical": "Ammonia", "Score": 0.36418090000000003, "CASStandard": "7664-41-7"}, {"Pounds": 7663.0, "ChemicalNumber": 124, "Chemical": "Chlorine", "Score": 1374.839, "CASStandard": "7782-50-5"}, {"Pounds": 84.0, "ChemicalNumber": 566, "Chemical": "Trichloroethane, 1,1,2-", "Score": 3.616403, "CASStandard": "79-00-5"}, {"Pounds": 8.0, "ChemicalNumber": 529, "Chemical": "Tetrachloroethane, 1,1,2,2-", "Score": 12.610859999999999, "CASStandard": "79-34-5"}, {"Pounds": 0.0002205, "ChemicalNumber": 614, "Chemical": "Dioxin and dioxin-like compounds", "Score": 0.0, "CASStandard": "N150"}]}, "2005": {"state_score_percentile": 78, "us_pounds_percentile": 77, "TotalPounds": 23648.600220499997, "us_score_percentile": 82, "state_pounds_percentile": 72, "TotalScore": 4165.591690278489, "Submissions": [{"Pounds": 3595.0, "ChemicalNumber": 222, "Chemical": "Dichloroethane, 1,2-", "Score": 2566.0699999999997, "CASStandard": "107-06-2"}, {"Pounds": 5.0, "ChemicalNumber": 135, "Chemical": "Chlorobenzene", "Score": 0.0001331927, "CASStandard": "108-90-7"}, {"Pounds": 3.0, "ChemicalNumber": 63, "Chemical": "Bis(2-chloroethyl)ether", "Score": 26.4896, "CASStandard": "111-44-4"}, {"Pounds": 2960.0, "ChemicalNumber": 491, "Chemical": "Propylene (Propene)", "Score": 0.02266492774, "CASStandard": "115-07-1"}, {"Pounds": 8.0, "ChemicalNumber": 531, "Chemical": "Tetrachloroethylene (Perchloroethylene)", "Score": 0.05603008, "CASStandard": "127-18-4"}, {"Pounds": 44.0, "ChemicalNumber": 223, "Chemical": "Dichloroethylene, 1,2-", "Score": 0.035863530000000005, "CASStandard": "540-59-0"}, {"Pounds": 13.0, "ChemicalNumber": 115, "Chemical": "Carbon tetrachloride", "Score": 2.061286, "CASStandard": "56-23-5"}, {"Pounds": 75.0, "ChemicalNumber": 140, "Chemical": "Chloroform", "Score": 47.6625, "CASStandard": "67-66-3"}, {"Pounds": 4054.0, "ChemicalNumber": 291, "Chemical": "Ethylene", "Score": 0.016639708, "CASStandard": "74-85-1"}, {"Pounds": 7.6, "ChemicalNumber": 346, "Chemical": "Lead and lead compounds", "Score": 1.30876, "CASStandard": "7439-92-1"}, {"Pounds": 78.0, "ChemicalNumber": 139, "Chemical": "Chloroethane (Ethyl chloride)", "Score": 0.00020411005, "CASStandard": "75-00-3"}, {"Pounds": 921.0, "ChemicalNumber": 586, "Chemical": "Vinyl chloride", "Score": 211.7273, "CASStandard": "75-01-4"}, {"Pounds": 1.0, "ChemicalNumber": 587, "Chemical": "Vinylidene chloride", "Score": 0.00012713, "CASStandard": "75-35-4"}, {"Pounds": 3416.0, "ChemicalNumber": 331, "Chemical": "Hydrochloric acid", "Score": 4.808807, "CASStandard": "7647-01-0"}, {"Pounds": 1243.0, "ChemicalNumber": 29, "Chemical": "Ammonia", "Score": 0.3423446, "CASStandard": "7664-41-7"}, {"Pounds": 7130.0, "ChemicalNumber": 124, "Chemical": "Chlorine", "Score": 1288.593, "CASStandard": "7782-50-5"}, {"Pounds": 87.0, "ChemicalNumber": 566, "Chemical": "Trichloroethane, 1,1,2-", "Score": 3.75047, "CASStandard": "79-00-5"}, {"Pounds": 8.0, "ChemicalNumber": 529, "Chemical": "Tetrachloroethane, 1,1,2,2-", "Score": 12.64596, "CASStandard": "79-34-5"}, {"Pounds": 0.0002205, "ChemicalNumber": 614, "Chemical": "Dioxin and dioxin-like compounds", "Score": 0.0, "CASStandard": "N150"}]}, "2006": {"state_score_percentile": 81, "us_pounds_percentile": 85, "TotalPounds": 55889.8002205, "us_score_percentile": 86, "state_pounds_percentile": 82, "TotalScore": 8883.78173697384, "Submissions": [{"Pounds": 8902.0, "ChemicalNumber": 222, "Chemical": "Dichloroethane, 1,2-", "Score": 6342.76, "CASStandard": "107-06-2"}, {"Pounds": 6.0, "ChemicalNumber": 135, "Chemical": "Chlorobenzene", "Score": 0.0001612001, "CASStandard": "108-90-7"}, {"Pounds": 2.0, "ChemicalNumber": 63, "Chemical": "Bis(2-chloroethyl)ether", "Score": 17.7045, "CASStandard": "111-44-4"}, {"Pounds": 5804.0, "ChemicalNumber": 491, "Chemical": "Propylene (Propene)", "Score": 0.0453254, "CASStandard": "115-07-1"}, {"Pounds": 8.0, "ChemicalNumber": 531, "Chemical": "Tetrachloroethylene (Perchloroethylene)", "Score": 0.056185650000000004, "CASStandard": "127-18-4"}, {"Pounds": 44.0, "ChemicalNumber": 223, "Chemical": "Dichloroethylene, 1,2-", "Score": 0.03603713, "CASStandard": "540-59-0"}, {"Pounds": 14.0, "ChemicalNumber": 115, "Chemical": "Carbon tetrachloride", "Score": 2.242677, "CASStandard": "56-23-5"}, {"Pounds": 92.0, "ChemicalNumber": 140, "Chemical": "Chloroform", "Score": 58.922000000000004, "CASStandard": "67-66-3"}, {"Pounds": 7127.0, "ChemicalNumber": 291, "Chemical": "Ethylene", "Score": 0.0290384, "CASStandard": "74-85-1"}, {"Pounds": 7.8, "ChemicalNumber": 346, "Chemical": "Lead and lead compounds", "Score": 1.34662, "CASStandard": "7439-92-1"}, {"Pounds": 75.0, "ChemicalNumber": 139, "Chemical": "Chloroethane (Ethyl chloride)", "Score": 0.00019691474, "CASStandard": "75-00-3"}, {"Pounds": 4850.0, "ChemicalNumber": 586, "Chemical": "Vinyl chloride", "Score": 1101.808, "CASStandard": "75-01-4"}, {"Pounds": 1.0, "ChemicalNumber": 587, "Chemical": "Vinylidene chloride", "Score": 0.000127449, "CASStandard": "75-35-4"}, {"Pounds": 16510.0, "ChemicalNumber": 138, "Chemical": "Chlorodifluoromethane (HCFC-22)", "Score": 0.00916793, "CASStandard": "75-45-6"}, {"Pounds": 3563.0, "ChemicalNumber": 331, "Chemical": "Hydrochloric acid", "Score": 5.038819, "CASStandard": "7647-01-0"}, {"Pounds": 1416.0, "ChemicalNumber": 29, "Chemical": "Ammonia", "Score": 0.3892219, "CASStandard": "7664-41-7"}, {"Pounds": 7382.0, "ChemicalNumber": 124, "Chemical": "Chlorine", "Score": 1337.343, "CASStandard": "7782-50-5"}, {"Pounds": 78.0, "ChemicalNumber": 566, "Chemical": "Trichloroethane, 1,1,2-", "Score": 3.369599, "CASStandard": "79-00-5"}, {"Pounds": 8.0, "ChemicalNumber": 529, "Chemical": "Tetrachloroethane, 1,1,2,2-", "Score": 12.68106, "CASStandard": "79-34-5"}, {"Pounds": 0.0002205, "ChemicalNumber": 614, "Chemical": "Dioxin and dioxin-like compounds", "Score": 0.0, "CASStandard": "N150"}]}, "2007": {"state_score_percentile": 82, "us_pounds_percentile": 85, "TotalPounds": 49326.100368676, "us_score_percentile": 86, "state_pounds_percentile": 82, "TotalScore": 9250.77533344258, "Submissions": [{"Pounds": 9644.0, "ChemicalNumber": 222, "Chemical": "Dichloroethane, 1,2-", "Score": 6896.46, "CASStandard": "107-06-2"}, {"Pounds": 7.0, "ChemicalNumber": 135, "Chemical": "Chlorobenzene", "Score": 0.0001894432, "CASStandard": "108-90-7"}, {"Pounds": 3.0, "ChemicalNumber": 63, "Chemical": "Bis(2-chloroethyl)ether", "Score": 26.624, "CASStandard": "111-44-4"}, {"Pounds": 5275.0, "ChemicalNumber": 491, "Chemical": "Propylene (Propene)", "Score": 0.041280700000000004, "CASStandard": "115-07-1"}, {"Pounds": 7.0, "ChemicalNumber": 531, "Chemical": "Tetrachloroethylene (Perchloroethylene)", "Score": 0.049349409999999996, "CASStandard": "127-18-4"}, {"Pounds": 51.0, "ChemicalNumber": 223, "Chemical": "Dichloroethylene, 1,2-", "Score": 0.04180862, "CASStandard": "540-59-0"}, {"Pounds": 15.0, "ChemicalNumber": 115, "Chemical": "Carbon tetrachloride", "Score": 2.407562, "CASStandard": "56-23-5"}, {"Pounds": 89.0, "ChemicalNumber": 140, "Chemical": "Chloroform", "Score": 57.189099999999996, "CASStandard": "67-66-3"}, {"Pounds": 1.0, "ChemicalNumber": 323, "Chemical": "Hexachloroethane", "Score": 0.105355, "CASStandard": "67-72-1"}, {"Pounds": 5869.0, "ChemicalNumber": 291, "Chemical": "Ethylene", "Score": 0.023852110000000003, "CASStandard": "74-85-1"}, {"Pounds": 8.1, "ChemicalNumber": 346, "Chemical": "Lead and lead compounds", "Score": 1.40197, "CASStandard": "7439-92-1"}, {"Pounds": 73.0, "ChemicalNumber": 156, "Chemical": "Copper and copper compounds", "Score": 0.795861, "CASStandard": "7440-50-8"}, {"Pounds": 72.0, "ChemicalNumber": 139, "Chemical": "Chloroethane (Ethyl chloride)", "Score": 0.00018954038, "CASStandard": "75-00-3"}, {"Pounds": 5109.0, "ChemicalNumber": 586, "Chemical": "Vinyl chloride", "Score": 1165.203, "CASStandard": "75-01-4"}, {"Pounds": 1.0, "ChemicalNumber": 587, "Chemical": "Vinylidene chloride", "Score": 0.000127769, "CASStandard": "75-35-4"}, {"Pounds": 11720.0, "ChemicalNumber": 138, "Chemical": "Chlorodifluoromethane (HCFC-22)", "Score": 0.00653585, "CASStandard": "75-45-6"}, {"Pounds": 3444.0, "ChemicalNumber": 331, "Chemical": "Hydrochloric acid", "Score": 4.886044999999999, "CASStandard": "7647-01-0"}, {"Pounds": 1626.0, "ChemicalNumber": 29, "Chemical": "Ammonia", "Score": 0.44607600000000003, "CASStandard": "7664-41-7"}, {"Pounds": 6223.0, "ChemicalNumber": 124, "Chemical": "Chlorine", "Score": 1080.4067, "CASStandard": "7782-50-5"}, {"Pounds": 82.0, "ChemicalNumber": 566, "Chemical": "Trichloroethane, 1,1,2-", "Score": 3.548251, "CASStandard": "79-00-5"}, {"Pounds": 7.0, "ChemicalNumber": 529, "Chemical": "Tetrachloroethane, 1,1,2,2-", "Score": 11.138079999999999, "CASStandard": "79-34-5"}, {"Pounds": 0.000368676, "ChemicalNumber": 614, "Chemical": "Dioxin and dioxin-like compounds", "Score": 0.0, "CASStandard": "N150"}]}, "2008": {"state_score_percentile": 81, "us_pounds_percentile": 82, "TotalPounds": 30034.00051156, "us_score_percentile": 85, "state_pounds_percentile": 79, "TotalScore": 6697.101088722201, "Submissions": [{"Pounds": 7573.0, "ChemicalNumber": 222, "Chemical": "Dichloroethane, 1,2-", "Score": 5404.91, "CASStandard": "107-06-2"}, {"Pounds": 3.0, "ChemicalNumber": 135, "Chemical": "Chlorobenzene", "Score": 8.03959e-05, "CASStandard": "108-90-7"}, {"Pounds": 4.0, "ChemicalNumber": 63, "Chemical": "Bis(2-chloroethyl)ether", "Score": 36.02238, "CASStandard": "111-44-4"}, {"Pounds": 4438.0, "ChemicalNumber": 491, "Chemical": "Propylene (Propene)", "Score": 0.03489902, "CASStandard": "115-07-1"}, {"Pounds": 1.0, "ChemicalNumber": 145, "Chemical": "Chloroprene", "Score": 7.32209, "CASStandard": "126-99-8"}, {"Pounds": 8.0, "ChemicalNumber": 531, "Chemical": "Tetrachloroethylene (Perchloroethylene)", "Score": 0.056916499999999995, "CASStandard": "127-18-4"}, {"Pounds": 38.0, "ChemicalNumber": 223, "Chemical": "Dichloroethylene, 1,2-", "Score": 0.03124712, "CASStandard": "540-59-0"}, {"Pounds": 11.0, "ChemicalNumber": 115, "Chemical": "Carbon tetrachloride", "Score": 1.761924, "CASStandard": "56-23-5"}, {"Pounds": 34.0, "ChemicalNumber": 140, "Chemical": "Chloroform", "Score": 21.39345, "CASStandard": "67-66-3"}, {"Pounds": 7416.0, "ChemicalNumber": 291, "Chemical": "Ethylene", "Score": 0.0305102, "CASStandard": "74-85-1"}, {"Pounds": 107.0, "ChemicalNumber": 139, "Chemical": "Chloroethane (Ethyl chloride)", "Score": 0.0002862983, "CASStandard": "75-00-3"}, {"Pounds": 4113.0, "ChemicalNumber": 586, "Chemical": "Vinyl chloride", "Score": 940.357, "CASStandard": "75-01-4"}, {"Pounds": 1.0, "ChemicalNumber": 587, "Chemical": "Vinylidene chloride", "Score": 0.000128088, "CASStandard": "75-35-4"}, {"Pounds": 3350.0, "ChemicalNumber": 331, "Chemical": "Hydrochloric acid", "Score": 4.77236, "CASStandard": "7647-01-0"}, {"Pounds": 1387.0, "ChemicalNumber": 29, "Chemical": "Ammonia", "Score": 0.38464909999999997, "CASStandard": "7664-41-7"}, {"Pounds": 1472.0, "ChemicalNumber": 124, "Chemical": "Chlorine", "Score": 258.6894, "CASStandard": "7782-50-5"}, {"Pounds": 67.0, "ChemicalNumber": 566, "Chemical": "Trichloroethane, 1,1,2-", "Score": 2.903728, "CASStandard": "79-00-5"}, {"Pounds": 11.0, "ChemicalNumber": 529, "Chemical": "Tetrachloroethane, 1,1,2,2-", "Score": 17.87464, "CASStandard": "79-34-5"}, {"Pounds": 0.00051156, "ChemicalNumber": 614, "Chemical": "Dioxin and dioxin-like compounds", "Score": 0.5554, "CASStandard": "N150"}]}, "2009": {"state_score_percentile": 82, "us_pounds_percentile": 84, "TotalPounds": 28161.000556672, "us_score_percentile": 86, "state_pounds_percentile": 81, "TotalScore": 6723.42484222483, "Submissions": [{"Pounds": 5314.0, "ChemicalNumber": 222, "Chemical": "Dichloroethane, 1,2-", "Score": 3811.99, "CASStandard": "107-06-2"}, {"Pounds": 4.0, "ChemicalNumber": 135, "Chemical": "Chlorobenzene", "Score": 0.0001085725, "CASStandard": "108-90-7"}, {"Pounds": 2.0, "ChemicalNumber": 63, "Chemical": "Bis(2-chloroethyl)ether", "Score": 17.839, "CASStandard": "111-44-4"}, {"Pounds": 2917.0, "ChemicalNumber": 491, "Chemical": "Propylene (Propene)", "Score": 0.02298422, "CASStandard": "115-07-1"}, {"Pounds": 6.0, "ChemicalNumber": 531, "Chemical": "Tetrachloroethylene (Perchloroethylene)", "Score": 0.04259773, "CASStandard": "127-18-4"}, {"Pounds": 1.0, "ChemicalNumber": 41, "Chemical": "Asbestos (friable)", "Score": 1247.98, "CASStandard": "1332-21-4"}, {"Pounds": 30.0, "ChemicalNumber": 223, "Chemical": "Dichloroethylene, 1,2-", "Score": 0.02468591, "CASStandard": "540-59-0"}, {"Pounds": 11.0, "ChemicalNumber": 115, "Chemical": "Carbon tetrachloride", "Score": 1.7768449999999998, "CASStandard": "56-23-5"}, {"Pounds": 65.0, "ChemicalNumber": 140, "Chemical": "Chloroform", "Score": 41.9402, "CASStandard": "67-66-3"}, {"Pounds": 7188.0, "ChemicalNumber": 291, "Chemical": "Ethylene", "Score": 0.0296258, "CASStandard": "74-85-1"}, {"Pounds": 63.0, "ChemicalNumber": 139, "Chemical": "Chloroethane (Ethyl chloride)", "Score": 0.00016658533, "CASStandard": "75-00-3"}, {"Pounds": 5649.0, "ChemicalNumber": 586, "Chemical": "Vinyl chloride", "Score": 1306.327, "CASStandard": "75-01-4"}, {"Pounds": 1.0, "ChemicalNumber": 587, "Chemical": "Vinylidene chloride", "Score": 0.000128407, "CASStandard": "75-35-4"}, {"Pounds": 3646.0, "ChemicalNumber": 331, "Chemical": "Hydrochloric acid", "Score": 5.220382, "CASStandard": "7647-01-0"}, {"Pounds": 1618.0, "ChemicalNumber": 29, "Chemical": "Ammonia", "Score": 0.447323, "CASStandard": "7664-41-7"}, {"Pounds": 1582.0, "ChemicalNumber": 124, "Chemical": "Chlorine", "Score": 278.4687, "CASStandard": "7782-50-5"}, {"Pounds": 59.0, "ChemicalNumber": 566, "Chemical": "Trichloroethane, 1,1,2-", "Score": 2.572638, "CASStandard": "79-00-5"}, {"Pounds": 5.0, "ChemicalNumber": 529, "Chemical": "Tetrachloroethane, 1,1,2,2-", "Score": 7.93071, "CASStandard": "79-34-5"}, {"Pounds": 0.000556672, "ChemicalNumber": 614, "Chemical": "Dioxin and dioxin-like compounds", "Score": 0.811747, "CASStandard": "N150"}]}, "2010": {"state_score_percentile": 82, "us_pounds_percentile": 83, "TotalPounds": 27612.300406181, "us_score_percentile": 87, "state_pounds_percentile": 80, "TotalScore": 7672.30137243545, "Submissions": [{"Pounds": 7336.0, "ChemicalNumber": 222, "Chemical": "Dichloroethane, 1,2-", "Score": 5298.85, "CASStandard": "107-06-2"}, {"Pounds": 4.0, "ChemicalNumber": 135, "Chemical": "Chlorobenzene", "Score": 0.000108941, "CASStandard": "108-90-7"}, {"Pounds": 3.0, "ChemicalNumber": 63, "Chemical": "Bis(2-chloroethyl)ether", "Score": 26.8257, "CASStandard": "111-44-4"}, {"Pounds": 5675.0, "ChemicalNumber": 491, "Chemical": "Propylene (Propene)", "Score": 0.044662099999999996, "CASStandard": "115-07-1"}, {"Pounds": 7.0, "ChemicalNumber": 531, "Chemical": "Tetrachloroethylene (Perchloroethylene)", "Score": 0.04976299, "CASStandard": "127-18-4"}, {"Pounds": 1.0, "ChemicalNumber": 41, "Chemical": "Asbestos (friable)", "Score": 1251.13, "CASStandard": "1332-21-4"}, {"Pounds": 1.0, "ChemicalNumber": 217, "Chemical": "Dichlorobenzene (mixed isomers)", "Score": 0.000136178, "CASStandard": "25321-22-6"}, {"Pounds": 41.0, "ChemicalNumber": 223, "Chemical": "Dichloroethylene, 1,2-", "Score": 0.03406112, "CASStandard": "540-59-0"}, {"Pounds": 15.0, "ChemicalNumber": 115, "Chemical": "Carbon tetrachloride", "Score": 2.439538, "CASStandard": "56-23-5"}, {"Pounds": 121.0, "ChemicalNumber": 140, "Chemical": "Chloroform", "Score": 79.0702, "CASStandard": "67-66-3"}, {"Pounds": 4517.0, "ChemicalNumber": 291, "Chemical": "Ethylene", "Score": 0.0185175, "CASStandard": "74-85-1"}, {"Pounds": 39.6, "ChemicalNumber": 156, "Chemical": "Copper and copper compounds", "Score": 0.433189, "CASStandard": "7440-50-8"}, {"Pounds": 70.0, "ChemicalNumber": 139, "Chemical": "Chloroethane (Ethyl chloride)", "Score": 0.00018587944999999998, "CASStandard": "75-00-3"}, {"Pounds": 3060.0, "ChemicalNumber": 586, "Chemical": "Vinyl chloride", "Score": 700.883, "CASStandard": "75-01-4"}, {"Pounds": 1.0, "ChemicalNumber": 587, "Chemical": "Vinylidene chloride", "Score": 0.000128727, "CASStandard": "75-35-4"}, {"Pounds": 3425.0, "ChemicalNumber": 331, "Chemical": "Hydrochloric acid", "Score": 4.91973, "CASStandard": "7647-01-0"}, {"Pounds": 1551.7, "ChemicalNumber": 29, "Chemical": "Ammonia", "Score": 0.43140500000000004, "CASStandard": "7664-41-7"}, {"Pounds": 1664.0, "ChemicalNumber": 124, "Chemical": "Chlorine", "Score": 293.6568, "CASStandard": "7782-50-5"}, {"Pounds": 73.0, "ChemicalNumber": 566, "Chemical": "Trichloroethane, 1,1,2-", "Score": 3.192687, "CASStandard": "79-00-5"}, {"Pounds": 1.0, "ChemicalNumber": 567, "Chemical": "Trichloroethylene", "Score": 0.112261, "CASStandard": "79-01-6"}, {"Pounds": 6.0, "ChemicalNumber": 529, "Chemical": "Tetrachloroethane, 1,1,2,2-", "Score": 9.54086, "CASStandard": "79-34-5"}, {"Pounds": 0.000406181, "ChemicalNumber": 614, "Chemical": "Dioxin and dioxin-like compounds", "Score": 0.668439, "CASStandard": "N150"}]}, "2011": {"state_score_percentile": 89, "us_pounds_percentile": 87, "TotalPounds": 46498.90124571, "us_score_percentile": 93, "state_pounds_percentile": 85, "TotalScore": 33164.22427741935, "Submissions": [{"Pounds": 6790.0, "ChemicalNumber": 222, "Chemical": "Dichloroethane, 1,2-", "Score": 4934.04, "CASStandard": "107-06-2"}, {"Pounds": 6.0, "ChemicalNumber": 135, "Chemical": "Chlorobenzene", "Score": 0.0001641676, "CASStandard": "108-90-7"}, {"Pounds": 4.0, "ChemicalNumber": 63, "Chemical": "Bis(2-chloroethyl)ether", "Score": 36.38876, "CASStandard": "111-44-4"}, {"Pounds": 3674.0, "ChemicalNumber": 491, "Chemical": "Propylene (Propene)", "Score": 0.029181139999999998, "CASStandard": "115-07-1"}, {"Pounds": 9.0, "ChemicalNumber": 531, "Chemical": "Tetrachloroethylene (Perchloroethylene)", "Score": 0.0645684, "CASStandard": "127-18-4"}, {"Pounds": 20.0, "ChemicalNumber": 41, "Chemical": "Asbestos (friable)", "Score": 25117.6, "CASStandard": "1332-21-4"}, {"Pounds": 38.0, "ChemicalNumber": 223, "Chemical": "Dichloroethylene, 1,2-", "Score": 0.03158736, "CASStandard": "540-59-0"}, {"Pounds": 16.0, "ChemicalNumber": 115, "Chemical": "Carbon tetrachloride", "Score": 2.63103, "CASStandard": "56-23-5"}, {"Pounds": 2.0, "ChemicalNumber": 530, "Chemical": "Tetrachloroethane, 1,1,1,2-", "Score": 0.0421775, "CASStandard": "630-20-6"}, {"Pounds": 145.0, "ChemicalNumber": 140, "Chemical": "Chloroform", "Score": 93.548, "CASStandard": "67-66-3"}, {"Pounds": 6.0, "ChemicalNumber": 51, "Chemical": "Benzene", "Score": 1.27013, "CASStandard": "71-43-2"}, {"Pounds": 3212.0, "ChemicalNumber": 291, "Chemical": "Ethylene", "Score": 0.0132082, "CASStandard": "74-85-1"}, {"Pounds": 7.9, "ChemicalNumber": 346, "Chemical": "Lead and lead compounds", "Score": 1.38299, "CASStandard": "7439-92-1"}, {"Pounds": 74.0, "ChemicalNumber": 139, "Chemical": "Chloroethane (Ethyl chloride)", "Score": 0.00019706075, "CASStandard": "75-00-3"}, {"Pounds": 11471.0, "ChemicalNumber": 586, "Chemical": "Vinyl chloride", "Score": 2614.665, "CASStandard": "75-01-4"}, {"Pounds": 1.0, "ChemicalNumber": 587, "Chemical": "Vinylidene chloride", "Score": 0.000129211, "CASStandard": "75-35-4"}, {"Pounds": 16490.0, "ChemicalNumber": 138, "Chemical": "Chlorodifluoromethane (HCFC-22)", "Score": 0.00936358, "CASStandard": "75-45-6"}, {"Pounds": 1159.0, "ChemicalNumber": 331, "Chemical": "Hydrochloric acid", "Score": 1.604298, "CASStandard": "7647-01-0"}, {"Pounds": 1318.0, "ChemicalNumber": 29, "Chemical": "Ammonia", "Score": 0.3713268, "CASStandard": "7664-41-7"}, {"Pounds": 1956.0, "ChemicalNumber": 124, "Chemical": "Chlorine", "Score": 345.9694, "CASStandard": "7782-50-5"}, {"Pounds": 93.0, "ChemicalNumber": 566, "Chemical": "Trichloroethane, 1,1,2-", "Score": 4.11777, "CASStandard": "79-00-5"}, {"Pounds": 1.0, "ChemicalNumber": 567, "Chemical": "Trichloroethylene", "Score": 0.112686, "CASStandard": "79-01-6"}, {"Pounds": 6.0, "ChemicalNumber": 529, "Chemical": "Tetrachloroethane, 1,1,2,2-", "Score": 9.57706, "CASStandard": "79-34-5"}, {"Pounds": 0.00124571, "ChemicalNumber": 614, "Chemical": "Dioxin and dioxin-like compounds", "Score": 0.75525, "CASStandard": "N150"}]}, "2012": {"state_score_percentile": 90, "us_pounds_percentile": 81, "TotalPounds": 21956.90125531, "us_score_percentile": 93, "state_pounds_percentile": 79, "TotalScore": 32664.519556774747, "Submissions": [{"Pounds": 8094.0, "ChemicalNumber": 222, "Chemical": "Dichloroethane, 1,2-", "Score": 5928.99, "CASStandard": "107-06-2"}, {"Pounds": 9.0, "ChemicalNumber": 135, "Chemical": "Chlorobenzene", "Score": 0.0002500298, "CASStandard": "108-90-7"}, {"Pounds": 4.0, "ChemicalNumber": 63, "Chemical": "Bis(2-chloroethyl)ether", "Score": 36.5512, "CASStandard": "111-44-4"}, {"Pounds": 34.0, "ChemicalNumber": 531, "Chemical": "Tetrachloroethylene (Perchloroethylene)", "Score": 0.25470729999999997, "CASStandard": "127-18-4"}, {"Pounds": 20.0, "ChemicalNumber": 41, "Chemical": "Asbestos (friable)", "Score": 25219.5, "CASStandard": "1332-21-4"}, {"Pounds": 1.0, "ChemicalNumber": 217, "Chemical": "Dichlorobenzene (mixed isomers)", "Score": 0.000146293, "CASStandard": "25321-22-6"}, {"Pounds": 42.0, "ChemicalNumber": 223, "Chemical": "Dichloroethylene, 1,2-", "Score": 0.035275, "CASStandard": "540-59-0"}, {"Pounds": 16.0, "ChemicalNumber": 115, "Chemical": "Carbon tetrachloride", "Score": 2.65441, "CASStandard": "56-23-5"}, {"Pounds": 3.0, "ChemicalNumber": 530, "Chemical": "Tetrachloroethane, 1,1,1,2-", "Score": 0.0636225, "CASStandard": "630-20-6"}, {"Pounds": 173.0, "ChemicalNumber": 140, "Chemical": "Chloroform", "Score": 112.8878, "CASStandard": "67-66-3"}, {"Pounds": 6.0, "ChemicalNumber": 51, "Chemical": "Benzene", "Score": 1.27528, "CASStandard": "71-43-2"}, {"Pounds": 4003.0, "ChemicalNumber": 291, "Chemical": "Ethylene", "Score": 0.016565530000000002, "CASStandard": "74-85-1"}, {"Pounds": 7.9, "ChemicalNumber": 346, "Chemical": "Lead and lead compounds", "Score": 1.3886, "CASStandard": "7439-92-1"}, {"Pounds": 79.0, "ChemicalNumber": 139, "Chemical": "Chloroethane (Ethyl chloride)", "Score": 0.00021139095, "CASStandard": "75-00-3"}, {"Pounds": 4202.0, "ChemicalNumber": 586, "Chemical": "Vinyl chloride", "Score": 973.7260000000001, "CASStandard": "75-01-4"}, {"Pounds": 1.0, "ChemicalNumber": 587, "Chemical": "Vinylidene chloride", "Score": 0.000129731, "CASStandard": "75-35-4"}, {"Pounds": 1277.0, "ChemicalNumber": 331, "Chemical": "Hydrochloric acid", "Score": 1.7964790000000002, "CASStandard": "7647-01-0"}, {"Pounds": 1738.0, "ChemicalNumber": 29, "Chemical": "Ammonia", "Score": 0.485691, "CASStandard": "7664-41-7"}, {"Pounds": 2046.0, "ChemicalNumber": 124, "Chemical": "Chlorine", "Score": 362.252, "CASStandard": "7782-50-5"}, {"Pounds": 106.0, "ChemicalNumber": 566, "Chemical": "Trichloroethane, 1,1,2-", "Score": 4.75467, "CASStandard": "79-00-5"}, {"Pounds": 91.0, "ChemicalNumber": 567, "Chemical": "Trichloroethylene", "Score": 10.892942, "CASStandard": "79-01-6"}, {"Pounds": 4.0, "ChemicalNumber": 529, "Chemical": "Tetrachloroethane, 1,1,2,2-", "Score": 6.41061, "CASStandard": "79-34-5"}, {"Pounds": 0.00125531, "ChemicalNumber": 614, "Chemical": "Dioxin and dioxin-like compounds", "Score": 0.582967, "CASStandard": "N150"}]}, "2013": {"state_score_percentile": 91, "us_pounds_percentile": 88, "TotalPounds": 48489.40105487, "us_score_percentile": 93, "state_pounds_percentile": 85, "TotalScore": 33917.8880049219, "Submissions": [{"Pounds": 9542.0, "ChemicalNumber": 222, "Chemical": "Dichloroethane, 1,2-", "Score": 7083.85, "CASStandard": "107-06-2"}, {"Pounds": 11.0, "ChemicalNumber": 135, "Chemical": "Chlorobenzene", "Score": 0.0003083798, "CASStandard": "108-90-7"}, {"Pounds": 4.0, "ChemicalNumber": 63, "Chemical": "Bis(2-chloroethyl)ether", "Score": 37.2392, "CASStandard": "111-44-4"}, {"Pounds": 4100.0, "ChemicalNumber": 491, "Chemical": "Propylene (Propene)", "Score": 0.03283044, "CASStandard": "115-07-1"}, {"Pounds": 12.0, "ChemicalNumber": 531, "Chemical": "Tetrachloroethylene (Perchloroethylene)", "Score": 0.0880065, "CASStandard": "127-18-4"}, {"Pounds": 20.0, "ChemicalNumber": 41, "Chemical": "Asbestos (friable)", "Score": 25325.6, "CASStandard": "1332-21-4"}, {"Pounds": 1.0, "ChemicalNumber": 217, "Chemical": "Dichlorobenzene (mixed isomers)", "Score": 0.000147134, "CASStandard": "25321-22-6"}, {"Pounds": 54.0, "ChemicalNumber": 223, "Chemical": "Dichloroethylene, 1,2-", "Score": 0.0458153, "CASStandard": "540-59-0"}, {"Pounds": 25.0, "ChemicalNumber": 115, "Chemical": "Carbon tetrachloride", "Score": 4.19612, "CASStandard": "56-23-5"}, {"Pounds": 4.0, "ChemicalNumber": 530, "Chemical": "Tetrachloroethane, 1,1,1,2-", "Score": 0.0853176, "CASStandard": "630-20-6"}, {"Pounds": 264.0, "ChemicalNumber": 140, "Chemical": "Chloroform", "Score": 174.5963, "CASStandard": "67-66-3"}, {"Pounds": 6.0, "ChemicalNumber": 51, "Chemical": "Benzene", "Score": 1.28064, "CASStandard": "71-43-2"}, {"Pounds": 3894.0, "ChemicalNumber": 291, "Chemical": "Ethylene", "Score": 0.01623883, "CASStandard": "74-85-1"}, {"Pounds": 8.4, "ChemicalNumber": 346, "Chemical": "Lead and lead compounds", "Score": 1.4827, "CASStandard": "7439-92-1"}, {"Pounds": 74.0, "ChemicalNumber": 139, "Chemical": "Chloroethane (Ethyl chloride)", "Score": 0.0001994361, "CASStandard": "75-00-3"}, {"Pounds": 4144.0, "ChemicalNumber": 586, "Chemical": "Vinyl chloride", "Score": 971.385, "CASStandard": "75-01-4"}, {"Pounds": 2.0, "ChemicalNumber": 587, "Chemical": "Vinylidene chloride", "Score": 0.00026480199999999996, "CASStandard": "75-35-4"}, {"Pounds": 21033.0, "ChemicalNumber": 138, "Chemical": "Chlorodifluoromethane (HCFC-22)", "Score": 0.0120795, "CASStandard": "75-45-6"}, {"Pounds": 1311.0, "ChemicalNumber": 331, "Chemical": "Hydrochloric acid", "Score": 1.849491, "CASStandard": "7647-01-0"}, {"Pounds": 2134.0, "ChemicalNumber": 29, "Chemical": "Ammonia", "Score": 0.59459, "CASStandard": "7664-41-7"}, {"Pounds": 1606.0, "ChemicalNumber": 124, "Chemical": "Chlorine", "Score": 287.1503, "CASStandard": "7782-50-5"}, {"Pounds": 124.0, "ChemicalNumber": 566, "Chemical": "Trichloroethane, 1,1,2-", "Score": 5.6184899999999995, "CASStandard": "79-00-5"}, {"Pounds": 92.0, "ChemicalNumber": 567, "Chemical": "Trichloroethylene", "Score": 11.069033999999998, "CASStandard": "79-01-6"}, {"Pounds": 6.0, "ChemicalNumber": 529, "Chemical": "Tetrachloroethane, 1,1,2,2-", "Score": 9.65636, "CASStandard": "79-34-5"}, {"Pounds": 18.0, "ChemicalNumber": 402, "Chemical": "Naphthalene", "Score": 1.48211, "CASStandard": "91-20-3"}, {"Pounds": 0.00105487, "ChemicalNumber": 614, "Chemical": "Dioxin and dioxin-like compounds", "Score": 0.556462, "CASStandard": "N150"}]}, "2014": {"state_score_percentile": 91, "us_pounds_percentile": 88, "TotalPounds": 46359.400986076, "us_score_percentile": 93, "state_pounds_percentile": 86, "TotalScore": 35118.35192296178, "Submissions": [{"Pounds": 10845.0, "ChemicalNumber": 222, "Chemical": "Dichloroethane, 1,2-", "Score": 8090.34, "CASStandard": "107-06-2"}, {"Pounds": 10.0, "ChemicalNumber": 135, "Chemical": "Chlorobenzene", "Score": 0.0002832078, "CASStandard": "108-90-7"}, {"Pounds": 5.0, "ChemicalNumber": 63, "Chemical": "Bis(2-chloroethyl)ether", "Score": 46.5202, "CASStandard": "111-44-4"}, {"Pounds": 4150.0, "ChemicalNumber": 491, "Chemical": "Propylene (Propene)", "Score": 0.03338471, "CASStandard": "115-07-1"}, {"Pounds": 11.0, "ChemicalNumber": 531, "Chemical": "Tetrachloroethylene (Perchloroethylene)", "Score": 0.0807849, "CASStandard": "127-18-4"}, {"Pounds": 20.0, "ChemicalNumber": 41, "Chemical": "Asbestos (friable)", "Score": 25436.3, "CASStandard": "1332-21-4"}, {"Pounds": 1.0, "ChemicalNumber": 217, "Chemical": "Dichlorobenzene (mixed isomers)", "Score": 0.000147999, "CASStandard": "25321-22-6"}, {"Pounds": 51.0, "ChemicalNumber": 223, "Chemical": "Dichloroethylene, 1,2-", "Score": 0.0435324, "CASStandard": "540-59-0"}, {"Pounds": 23.0, "ChemicalNumber": 115, "Chemical": "Carbon tetrachloride", "Score": 3.88317, "CASStandard": "56-23-5"}, {"Pounds": 4.0, "ChemicalNumber": 530, "Chemical": "Tetrachloroethane, 1,1,1,2-", "Score": 0.085819, "CASStandard": "630-20-6"}, {"Pounds": 256.0, "ChemicalNumber": 140, "Chemical": "Chloroform", "Score": 170.24030000000002, "CASStandard": "67-66-3"}, {"Pounds": 6.0, "ChemicalNumber": 51, "Chemical": "Benzene", "Score": 1.28623, "CASStandard": "71-43-2"}, {"Pounds": 4263.0, "ChemicalNumber": 291, "Chemical": "Ethylene", "Score": 0.01785611, "CASStandard": "74-85-1"}, {"Pounds": 8.4, "ChemicalNumber": 346, "Chemical": "Lead and lead compounds", "Score": 1.48918, "CASStandard": "7439-92-1"}, {"Pounds": 68.0, "ChemicalNumber": 139, "Chemical": "Chloroethane (Ethyl chloride)", "Score": 0.00018418, "CASStandard": "75-00-3"}, {"Pounds": 4438.0, "ChemicalNumber": 586, "Chemical": "Vinyl chloride", "Score": 1047.029, "CASStandard": "75-01-4"}, {"Pounds": 2.0, "ChemicalNumber": 587, "Chemical": "Vinylidene chloride", "Score": 0.00026616499999999996, "CASStandard": "75-35-4"}, {"Pounds": 17162.0, "ChemicalNumber": 138, "Chemical": "Chlorodifluoromethane (HCFC-22)", "Score": 0.00991429, "CASStandard": "75-45-6"}, {"Pounds": 1360.0, "ChemicalNumber": 331, "Chemical": "Hydrochloric acid", "Score": 1.926746, "CASStandard": "7647-01-0"}, {"Pounds": 1823.0, "ChemicalNumber": 29, "Chemical": "Ammonia", "Score": 0.513787, "CASStandard": "7664-41-7"}, {"Pounds": 1615.0, "ChemicalNumber": 124, "Chemical": "Chlorine", "Score": 290.08619999999996, "CASStandard": "7782-50-5"}, {"Pounds": 121.0, "ChemicalNumber": 566, "Chemical": "Trichloroethane, 1,1,2-", "Score": 5.51302, "CASStandard": "79-00-5"}, {"Pounds": 91.0, "ChemicalNumber": 567, "Chemical": "Trichloroethylene", "Score": 11.019712, "CASStandard": "79-01-6"}, {"Pounds": 6.0, "ChemicalNumber": 529, "Chemical": "Tetrachloroethane, 1,1,2,2-", "Score": 9.69855, "CASStandard": "79-34-5"}, {"Pounds": 20.0, "ChemicalNumber": 402, "Chemical": "Naphthalene", "Score": 1.65386, "CASStandard": "91-20-3"}, {"Pounds": 0.000986076, "ChemicalNumber": 614, "Chemical": "Dioxin and dioxin-like compounds", "Score": 0.579795, "CASStandard": "N150"}]}}, "DUNS": "801912965", "X": -152, "LLNotes": "NULL", "County": "TX,SAN PATRICIO", "NPDESCOMID": "NULL", "DistanceToReach": 1064.67924974, "SICCode3Digit": "286", "DerivedSIC": "False", "PublicContactPhone": "3617766310", "ParentDUNS": "144374907", "HEM3ID": 12924, "SICCode2Digit": "28", "DistanceToHEM3": 29410.1716227, "STFIPS": "48", "City": "GREGORY", "FacilityID": "78359CCDNTHWY36", "ReportedReachName": "NULL", "ZIPCODE": "78359", "TribalLandName": "NULL", "FRSID": "NULL", "State": "TX", "Latitude": 27.886534, "NearCOMID": 1432761, "ModeledReleases": "True", "StackDiameterSource": "Fac Spec", "FacilityNumber": 48314, "StackDiameter": 0.9897, "StackHeightSource": "Fac Spec", "NAICSCode4Digit": "3251", "Region": 6, "RCRANumber": "NA", "OnTribalLand": "False", "OutfallSource": "NULL", "SIC5": "NULL", "SIC4": "NULL", "SIC7": "NULL", "SIC6": "NULL", "SIC1": {"siccode": "2869", "1988": {"us_count": 606, "state_count": 103, "us_score_pct": 41, "state_score_pct": 28, "state_pounds_pct": 21, "us_pounds_pct": 41}, "1989": {"us_count": 613, "state_count": 103, "us_score_pct": 48, "state_score_pct": 32, "state_pounds_pct": 28, "us_pounds_pct": 47}, "1990": {"us_count": 632, "state_count": 108, "us_score_pct": 53, "state_score_pct": 35, "state_pounds_pct": 37, "us_pounds_pct": 53}, "1991": {"us_count": 626, "state_count": 108, "us_score_pct": 70, "state_score_pct": 54, "state_pounds_pct": 59, "us_pounds_pct": 72}, "1992": {"us_count": 627, "state_count": 111, "us_score_pct": 70, "state_score_pct": 54, "state_pounds_pct": 56, "us_pounds_pct": 70}, "1993": {"us_count": 625, "state_count": 113, "us_score_pct": 70, "state_score_pct": 52, "state_pounds_pct": 62, "us_pounds_pct": 72}, "1994": {"us_count": 633, "state_count": 118, "us_score_pct": 71, "state_score_pct": 55, "state_pounds_pct": 62, "us_pounds_pct": 71}, "1995": {"us_count": 604, "state_count": 117, "us_score_pct": 63, "state_score_pct": 45, "state_pounds_pct": 49, "us_pounds_pct": 60}, "1996": {"us_count": 620, "state_count": 121, "us_score_pct": 65, "state_score_pct": 45, "state_pounds_pct": 52, "us_pounds_pct": 60}, "1997": {"us_count": 616, "state_count": 124, "us_score_pct": 66, "state_score_pct": 49, "state_pounds_pct": 55, "us_pounds_pct": 61}, "1998": {"us_count": 619, "state_count": 125, "us_score_pct": 70, "state_score_pct": 52, "state_pounds_pct": 56, "us_pounds_pct": 64}, "1999": {"us_count": 623, "state_count": 124, "us_score_pct": 69, "state_score_pct": 53, "state_pounds_pct": 52, "us_pounds_pct": 62}, "2000": {"us_count": 638, "state_count": 128, "us_score_pct": 72, "state_score_pct": 56, "state_pounds_pct": 57, "us_pounds_pct": 67}, "2001": {"us_count": 642, "state_count": 130, "us_score_pct": 64, "state_score_pct": 46, "state_pounds_pct": 54, "us_pounds_pct": 66}, "2002": {"us_count": 637, "state_count": 132, "us_score_pct": 64, "state_score_pct": 53, "state_pounds_pct": 47, "us_pounds_pct": 58}, "2003": {"us_count": 637, "state_count": 129, "us_score_pct": 64, "state_score_pct": 51, "state_pounds_pct": 48, "us_pounds_pct": 62}, "2004": {"us_count": 635, "state_count": 132, "us_score_pct": 60, "state_score_pct": 44, "state_pounds_pct": 42, "us_pounds_pct": 53}, "2005": {"us_count": 641, "state_count": 132, "us_score_pct": 61, "state_score_pct": 45, "state_pounds_pct": 44, "us_pounds_pct": 54}, "2006": {"us_count": 644, "state_count": 132, "us_score_pct": 68, "state_score_pct": 51, "state_pounds_pct": 60, "us_pounds_pct": 68}, "2007": {"us_count": 652, "state_count": 128, "us_score_pct": 69, "state_score_pct": 50, "state_pounds_pct": 57, "us_pounds_pct": 67}, "2008": {"us_count": 691, "state_count": 130, "us_score_pct": 69, "state_score_pct": 50, "state_pounds_pct": 52, "us_pounds_pct": 65}, "2009": {"us_count": 695, "state_count": 130, "us_score_pct": 71, "state_score_pct": 56, "state_pounds_pct": 53, "us_pounds_pct": 66}, "2010": {"us_count": 703, "state_count": 130, "us_score_pct": 72, "state_score_pct": 56, "state_pounds_pct": 55, "us_pounds_pct": 66}, "2011": {"us_count": 706, "state_count": 130, "us_score_pct": 86, "state_score_pct": 74, "state_pounds_pct": 63, "us_pounds_pct": 73}, "2012": {"us_count": 706, "state_count": 131, "us_score_pct": 85, "state_score_pct": 74, "state_pounds_pct": 52, "us_pounds_pct": 60}, "2013": {"us_count": 690, "state_count": 129, "us_score_pct": 86, "state_score_pct": 75, "state_pounds_pct": 63, "us_pounds_pct": 74}, "2014": {"us_count": 706, "state_count": 132, "us_score_pct": 87, "state_score_pct": 78, "state_pounds_pct": 65, "us_pounds_pct": 76}, "name": "INDUSTRIAL ORGANIC CHEMICALS, NEC"}, "SIC3": "NULL", "SIC2": {"siccode": "2812", "1988": {"us_count": 63, "state_count": 6, "us_score_pct": 47, "state_score_pct": 33, "state_pounds_pct": 50, "us_pounds_pct": 60}, "1989": {"us_count": 63, "state_count": 6, "us_score_pct": 61, "state_score_pct": 50, "state_pounds_pct": 50, "us_pounds_pct": 63}, "1990": {"us_count": 67, "state_count": 6, "us_score_pct": 68, "state_score_pct": 50, "state_pounds_pct": 50, "us_pounds_pct": 71}, "1991": {"us_count": 63, "state_count": 6, "us_score_pct": 74, "state_score_pct": 50, "state_pounds_pct": 66, "us_pounds_pct": 80}, "1992": {"us_count": 64, "state_count": 6, "us_score_pct": 79, "state_score_pct": 66, "state_pounds_pct": 66, "us_pounds_pct": 79}, "1993": {"us_count": 61, "state_count": 6, "us_score_pct": 81, "state_score_pct": 66, "state_pounds_pct": 83, "us_pounds_pct": 83}, "1994": {"us_count": 57, "state_count": 6, "us_score_pct": 80, "state_score_pct": 66, "state_pounds_pct": 66, "us_pounds_pct": 82}, "1995": {"us_count": 53, "state_count": 6, "us_score_pct": 79, "state_score_pct": 66, "state_pounds_pct": 66, "us_pounds_pct": 75}, "1996": {"us_count": 54, "state_count": 5, "us_score_pct": 79, "state_score_pct": 40, "state_pounds_pct": 60, "us_pounds_pct": 74}, "1997": {"us_count": 53, "state_count": 5, "us_score_pct": 81, "state_score_pct": 60, "state_pounds_pct": 60, "us_pounds_pct": 73}, "1998": {"us_count": 53, "state_count": 6, "us_score_pct": 79, "state_score_pct": 50, "state_pounds_pct": 66, "us_pounds_pct": 77}, "1999": {"us_count": 49, "state_count": 5, "us_score_pct": 77, "state_score_pct": 40, "state_pounds_pct": 60, "us_pounds_pct": 75}, "2000": {"us_count": 42, "state_count": 4, "us_score_pct": 76, "state_score_pct": 50, "state_pounds_pct": 50, "us_pounds_pct": 73}, "2001": {"us_count": 45, "state_count": 4, "us_score_pct": 71, "state_score_pct": 50, "state_pounds_pct": 50, "us_pounds_pct": 75}, "2002": {"us_count": 40, "state_count": 4, "us_score_pct": 67, "state_score_pct": 50, "state_pounds_pct": 50, "us_pounds_pct": 72}, "2003": {"us_count": 40, "state_count": 4, "us_score_pct": 70, "state_score_pct": 50, "state_pounds_pct": 50, "us_pounds_pct": 72}, "2004": {"us_count": 38, "state_count": 4, "us_score_pct": 63, "state_score_pct": 50, "state_pounds_pct": 50, "us_pounds_pct": 68}, "2005": {"us_count": 38, "state_count": 4, "us_score_pct": 65, "state_score_pct": 50, "state_pounds_pct": 50, "us_pounds_pct": 68}, "2006": {"us_count": 41, "state_count": 4, "us_score_pct": 75, "state_score_pct": 50, "state_pounds_pct": 50, "us_pounds_pct": 75}, "2007": {"us_count": 42, "state_count": 4, "us_score_pct": 78, "state_score_pct": 50, "state_pounds_pct": 50, "us_pounds_pct": 73}, "2008": {"us_count": 41, "state_count": 4, "us_score_pct": 75, "state_score_pct": 50, "state_pounds_pct": 50, "us_pounds_pct": 70}, "2009": {"us_count": 40, "state_count": 4, "us_score_pct": 75, "state_score_pct": 50, "state_pounds_pct": 50, "us_pounds_pct": 72}, "2010": {"us_count": 44, "state_count": 4, "us_score_pct": 79, "state_score_pct": 50, "state_pounds_pct": 50, "us_pounds_pct": 75}, "2011": {"us_count": 38, "state_count": 4, "us_score_pct": 78, "state_score_pct": 50, "state_pounds_pct": 50, "us_pounds_pct": 73}, "2012": {"us_count": 38, "state_count": 4, "us_score_pct": 76, "state_score_pct": 50, "state_pounds_pct": 50, "us_pounds_pct": 68}, "2013": {"us_count": 37, "state_count": 4, "us_score_pct": 75, "state_score_pct": 50, "state_pounds_pct": 50, "us_pounds_pct": 70}, "2014": {"us_count": 40, "state_count": 3, "us_score_pct": 80, "state_score_pct": 33, "state_pounds_pct": 33, "us_pounds_pct": 75}, "name": "ALKALIES AND CHLORINE"}, "NewIndustryFlag": "False", "NPDESReach": "NULL", "FacilityName": "OCCIDENTAL CHEMICAL CORP", "Y": 662, "GridCode": 14, "ChromHexPercent": 0.25, "ReachSource": "Manual", "StackVelocity": 8.9028, "FederalFacilityFlag": "NULL", "AssignedCOMID": -1, "NAICSCode3Digit": "325", "DerivedNAICS": "0", "NHDRegion": 12, "PCT_CH6": 0.25, "Street": "4133 HWY 361"}