{"NPDESYear": "NULL", "ChangedNAICS": "NULL", "LLYear": "2015", "LatLongSource": "FRS", "ReportedCOMID": "NULL", "NPDESPermit": "NULL", "ReportedReach": "NULL", "PublicContactName": "MICHAEL KORBER", "FederalAgencyName": "C", "ParentName": "NA", "ZIP9": "02724", "NAICS1": {"naicscode": "315991", "1994": {"us_count": 1, "state_count": 1, "us_score_pct": 100, "state_score_pct": 100, "state_pounds_pct": 100, "us_pounds_pct": 100}, "name": "Hat, Cap, and Millinery Manufacturing"}, "NAICS2": "NULL", "NAICS3": "NULL", "NAICS4": "NULL", "NAICS5": "NULL", "NAICS6": "NULL", "OutfallLatitude": "NULL", "StackVelocitySource": "SIC 3dig", "StackHeight": 6.096, "RadialDistance": 3098175, "NearReach": "NULL", "OutfallLongitude": "NULL", "AssignedReach": "NULL", "Longitude": -71.17266, "FIPS": "25005", "Emissions": {"1994": {"state_score_percentile": 42, "us_pounds_percentile": 94, "TotalPounds": 322500.0, "us_score_percentile": 53, "state_pounds_percentile": 97, "TotalScore": 106.50174, "Submissions": [{"Pounds": 249300.0, "ChemicalNumber": 549, "Chemical": "Toluene", "Score": 82.07293, "CASStandard": "108-88-3"}, {"Pounds": 73200.0, "ChemicalNumber": 373, "Chemical": "Methyl ethyl ketone", "Score": 24.428810000000002, "CASStandard": "78-93-3"}]}}, "DUNS": "001054535", "X": 2504, "LLNotes": "NULL", "County": "MA,BRISTOL", "NPDESCOMID": "NULL", "DistanceToReach": "NULL", "SICCode3Digit": "235", "DerivedSIC": "False", "PublicContactPhone": "5086727033", "ParentDUNS": "NA", "HEM3ID": 94726, "SICCode2Digit": "23", "DistanceToHEM3": 17825.8984767, "STFIPS": "25", "City": "FALL RIVER", "FacilityID": "02724KRBRH394KI", "ReportedReachName": "NULL", "ZIPCODE": "02724", "TribalLandName": "NULL", "FRSID": "NULL", "State": "MA", "Latitude": 41.68149, "NearCOMID": "NULL", "ModeledReleases": "True", "StackDiameterSource": "SIC 3dig", "FacilityNumber": 1836, "StackDiameter": 0.3795, "StackHeightSource": "SIC 3dig", "NAICSCode4Digit": "3159", "Region": 1, "RCRANumber": "NULL", "OnTribalLand": "False", "OutfallSource": "NULL", "SIC5": "NULL", "SIC4": "NULL", "SIC7": "NULL", "SIC6": "NULL", "SIC1": {"1994": {"us_count": 1, "state_count": 1, "us_score_pct": 100, "state_score_pct": 100, "state_pounds_pct": 100, "us_pounds_pct": 100}, "name": "HATS, CAPS, AND MILLINERY", "siccode": "2353"}, "SIC3": "NULL", "SIC2": "NULL", "NewIndustryFlag": "False", "NPDESReach": "NULL", "FacilityName": "KORBER HATS", "Y": 2891, "GridCode": 14, "ChromHexPercent": 0.34, "ReachSource": "NULL", "StackVelocity": 9.144, "FederalFacilityFlag": "NULL", "AssignedCOMID": "NULL", "NAICSCode3Digit": "315", "DerivedNAICS": "0", "NHDRegion": 1, "PCT_CH6": 0.34, "Street": "394 KILBURN ST."}