{"NPDESYear": "NULL", "ChangedNAICS": "NULL", "LLYear": "2015", "LatLongSource": "FRS", "ReportedCOMID": "NULL", "NPDESPermit": "NULL", "ReportedReach": "NULL", "PublicContactName": "PETE CARUSO", "FederalAgencyName": "C", "ParentName": "MOBEX CORP", "ZIP9": "10994", "NAICS1": {"naicscode": "332510", "name": "Hardware Manufacturing", "1990": {"us_count": 24, "state_count": 1, "us_score_pct": 54, "state_score_pct": 100, "state_pounds_pct": 100, "us_pounds_pct": 54}}, "NAICS2": "NULL", "NAICS3": "NULL", "NAICS4": "NULL", "NAICS5": "NULL", "NAICS6": "NULL", "OutfallLatitude": "NULL", "StackVelocitySource": "SIC 3dig", "StackHeight": 8.2296, "RadialDistance": 2871846, "NearReach": "NULL", "OutfallLongitude": "NULL", "AssignedReach": "NULL", "Longitude": -73.96219, "FIPS": "36087", "Emissions": {"1990": {"state_score_percentile": 77, "us_pounds_percentile": 53, "TotalPounds": 7697.0, "us_score_percentile": 74, "state_pounds_percentile": 44, "TotalScore": 557.558927, "Submissions": [{"Pounds": 2042.0, "ChemicalNumber": 594, "Chemical": "Zinc and zinc compounds", "Score": 39.161867, "CASStandard": "7440-66-6"}, {"Pounds": 5150.0, "ChemicalNumber": 331, "Chemical": "Hydrochloric acid", "Score": 178.29777, "CASStandard": "7647-01-0"}, {"Pounds": 505.0, "ChemicalNumber": 521, "Chemical": "Sulfuric acid", "Score": 340.09929, "CASStandard": "7664-93-9"}]}}, "DUNS": "081008706", "X": 2247, "LLNotes": "NULL", "County": "NY,ROCKLAND", "NPDESCOMID": "NULL", "DistanceToReach": "NULL", "SICCode3Digit": "342", "DerivedSIC": "False", "PublicContactPhone": "8168873456", "ParentDUNS": "NA", "HEM3ID": 94745, "SICCode2Digit": "34", "DistanceToHEM3": 21576.7285696, "STFIPS": "36", "City": "WEST NYACK", "FacilityID": "10994GRNTHHIGHS", "ReportedReachName": "NULL", "ZIPCODE": "10994", "TribalLandName": "NULL", "FRSID": "NULL", "State": "NY", "Latitude": 41.09349, "NearCOMID": "NULL", "ModeledReleases": "True", "StackDiameterSource": "SIC 3dig", "FacilityNumber": 5866, "StackDiameter": 0.4572, "StackHeightSource": "SIC 3dig", "NAICSCode4Digit": "3325", "Region": 2, "RCRANumber": "NYD075443283", "OnTribalLand": "False", "OutfallSource": "NULL", "SIC5": "NULL", "SIC4": "NULL", "SIC7": "NULL", "SIC6": "NULL", "SIC1": {"name": "HARDWARE, NEC", "1990": {"us_count": 23, "state_count": 1, "us_score_pct": 56, "state_score_pct": 100, "state_pounds_pct": 100, "us_pounds_pct": 56}, "siccode": "3429"}, "SIC3": "NULL", "SIC2": {"name": "METAL STAMPINGS, NEC", "1990": {"us_count": 64, "state_count": 7, "us_score_pct": 81, "state_score_pct": 85, "state_pounds_pct": 28, "us_pounds_pct": 39}, "siccode": "3469"}, "NewIndustryFlag": "False", "NPDESReach": "NULL", "FacilityName": "GRANT HARDWARE CO.", "Y": 2743, "GridCode": 14, "ChromHexPercent": 0.65, "ReachSource": "NULL", "StackVelocity": 9.0861, "FederalFacilityFlag": "NULL", "AssignedCOMID": "NULL", "NAICSCode3Digit": "332", "DerivedNAICS": "0", "NHDRegion": 2, "PCT_CH6": 0.65, "Street": "HIGH ST."}