{"NPDESYear": "NULL", "Confirmed": "False", "LatLongSource": "FRS", "FederalAgencyName": "NULL", "ParentName": "NULL", "LLYear": "2016", "NAICS1": {"naicscode": "337211", "name": "Wood Office Furniture Manufacturing"}, "NAICS2": "NULL", "NAICS3": "NULL", "NAICS4": "NULL", "NAICS5": "NULL", "NAICS6": "NULL", "OutfallLatitude": "NULL", "StackVelocitySource": "NAICS4", "StackHeight": 8.8392, "GridCode": 14, "OutfallLongitude": "NULL", "AssignedReach": "NULL", "Longitude": -71.98885, "FIPS": "25027", "Emissions": {}, "DUNS": "005995006", "X": 2393, "LLNotes": "NULL", "County": "MA,WORCESTER", "FRSID": "110001958383", "REGION": 1, "DistanceToReach": "NULL", "PublicContactPhone": "5086324700", "ParentDUNS": "005995006", "HEM3ID": 4780, "DistanceToHEM3": 19148.3401575, "STFIPS": "25", "City": "GARDNER", "FacilityID": "01440MDRNC424MA", "NearReach": "NULL", "ZIPCODE": "01440", "ChromSource": "Default", "State": "MA", "Latitude": 42.56871, "NearCOMID": "NULL", "OutfallSource": "NULL", "StackDiameterSource": "NAICS4", "FacilityNumber": 708, "StackDiameter": 0.762, "NAICSCode5Digit": "33721", "StackHeightSource": "NAICS4", "NAICSCode4Digit": "3372", "NearestTribalLand": "NULL", "RadialDistance": 3101200, "ModeledReleases": "False", "NewIndustryFlag": "False", "FacilityName": "MODERN CONTRACT FURNITURE INC", "Y": 2989, "WaterReleases": "False", "ModChromReleases": "False", "ChromHexPercent": 0.340000003576, "ReachSource": "NULL", "DistanceToTribalLand": "NULL", "StackVelocity": 10.06, "FederalFacilityFlag": "C", "PublicContactName": "ROLAND MARTEL", "NAICSCode3Digit": "337", "ZIP9": "01440", "NEIYear": "2011", "AssignedCOMID": "NULL", "Street": "424 MAIN ST"}