{"NPDESYear": "NULL", "Confirmed": "False", "LatLongSource": "FRS", "FederalAgencyName": "NULL", "ParentName": "NULL", "LLYear": "2016", "NAICS1": {"naicscode": "312120", "name": "Breweries"}, "NAICS2": "NULL", "NAICS3": "NULL", "NAICS4": "NULL", "NAICS5": "NULL", "NAICS6": "NULL", "OutfallLatitude": "NULL", "StackVelocitySource": "Fac Spec", "StackHeight": 7.62, "GridCode": 14, "OutfallLongitude": "NULL", "AssignedReach": "NULL", "Longitude": -75.629067, "FIPS": "42077", "Emissions": {}, "DUNS": "005357041", "X": 2095, "LLNotes": "NULL", "County": "PA,LEHIGH", "FRSID": "110000562980", "REGION": 3, "DistanceToReach": "NULL", "PublicContactPhone": "6103957522", "ParentDUNS": "005357041", "HEM3ID": 14737, "DistanceToHEM3": 18450.7651037, "STFIPS": "42", "City": "FOGELSVILLE", "FacilityID": "18051THSTRSWROU", "NearReach": "NULL", "ZIPCODE": "18051", "ChromSource": "Default", "State": "PA", "Latitude": 40.576396, "NearCOMID": "NULL", "OutfallSource": "NULL", "StackDiameterSource": "Fac Spec", "FacilityNumber": 9667, "StackDiameter": 0.0914, "NAICSCode5Digit": "31212", "StackHeightSource": "Fac Spec", "NAICSCode4Digit": "3121", "NearestTribalLand": "NULL", "RadialDistance": 2726550, "ModeledReleases": "False", "NewIndustryFlag": "False", "FacilityName": "PABST BREWING CO", "Y": 2635, "WaterReleases": "False", "ModChromReleases": "False", "ChromHexPercent": 0.340000003576, "ReachSource": "NULL", "DistanceToTribalLand": "NULL", "StackVelocity": 0.061, "FederalFacilityFlag": "C", "PublicContactName": "MIKE GRAY", "NAICSCode3Digit": "312", "ZIP9": "18051", "NEIYear": "2011", "AssignedCOMID": "NULL", "Street": "7880 STROH DR"}