{
    "AssignedComID": 9513646,
    "AssignedReach": "02030105000581",
    "City": "NEW BRUNSWICK",
    "County": "NJ,MIDDLESEX",
    "DUNS": "132412842",
    "DataSource": "",
    "DerivedSICCode": 0,
    "DistanceToHEM3": 34329.346586,
    "DistanceToReach": "",
    "DistanceToStream": "",
    "DistanceToWBAN": "",
    "Emissions": {
        "1996": {
            "Submissions": [
                {
                    "CASNumber": "108952",
                    "Chemical": "Phenol",
                    "ChemicalNumber": 454,
                    "DCN": "1396105042117",
                    "MaxOnsite": "05",
                    "Pounds": 2400.0,
                    "Score": 0.0,
                    "SubmissionNumber": 1793432,
                    "Use": "P"
                },
                {
                    "CASNumber": "67561",
                    "Chemical": "Methanol",
                    "ChemicalNumber": 364,
                    "DCN": "1396105042129",
                    "MaxOnsite": "04",
                    "Pounds": 22000.0,
                    "Score": 4.74554,
                    "SubmissionNumber": 1793433,
                    "Use": "OU"
                },
                {
                    "CASNumber": "108883",
                    "Chemical": "Toluene",
                    "ChemicalNumber": 549,
                    "DCN": "1396105042131",
                    "MaxOnsite": "04",
                    "Pounds": 43016.0,
                    "Score": 7.089119999999999,
                    "SubmissionNumber": 1793434,
                    "Use": "OU"
                }
            ],
            "TotalPounds": 67416.0,
            "TotalScore": 11.83466,
            "state_score_percentile": 92,
            "us_score_percentile": 81
        },
        "1997": {
            "Submissions": [
                {
                    "CASNumber": "67561",
                    "Chemical": "Methanol",
                    "ChemicalNumber": 364,
                    "DCN": "1397115049862",
                    "MaxOnsite": "04",
                    "Pounds": 23000.0,
                    "Score": 5.13283,
                    "SubmissionNumber": 1878541,
                    "Use": "OU"
                },
                {
                    "CASNumber": "108952",
                    "Chemical": "Phenol",
                    "ChemicalNumber": 454,
                    "DCN": "1397115049874",
                    "MaxOnsite": "05",
                    "Pounds": 2600.0,
                    "Score": 0.0,
                    "SubmissionNumber": 1878542,
                    "Use": "P"
                },
                {
                    "CASNumber": "108883",
                    "Chemical": "Toluene",
                    "ChemicalNumber": 549,
                    "DCN": "1397115049886",
                    "MaxOnsite": "",
                    "Pounds": 53072.0,
                    "Score": 9.18012,
                    "SubmissionNumber": 1878543,
                    "Use": "OU"
                }
            ],
            "TotalPounds": 78672.0,
            "TotalScore": 14.31295,
            "state_score_percentile": 93,
            "us_score_percentile": 84
        },
        "1998": {
            "Submissions": [
                {
                    "CASNumber": "108952",
                    "Chemical": "Phenol",
                    "ChemicalNumber": 454,
                    "DCN": "1398125008159",
                    "MaxOnsite": "05",
                    "Pounds": 2600.0,
                    "Score": 0.0,
                    "SubmissionNumber": 1967812,
                    "Use": "P"
                },
                {
                    "CASNumber": "67561",
                    "Chemical": "Methanol",
                    "ChemicalNumber": 364,
                    "DCN": "1398125008197",
                    "MaxOnsite": "04",
                    "Pounds": 16000.0,
                    "Score": 3.803483,
                    "SubmissionNumber": 1967816,
                    "Use": "OU"
                },
                {
                    "CASNumber": "108883",
                    "Chemical": "Toluene",
                    "ChemicalNumber": 549,
                    "DCN": "1398125008262",
                    "MaxOnsite": "04",
                    "Pounds": 64062.0,
                    "Score": 11.85532,
                    "SubmissionNumber": 1967823,
                    "Use": "OU"
                }
            ],
            "TotalPounds": 82662.0,
            "TotalScore": 15.658803,
            "state_score_percentile": 92,
            "us_score_percentile": 83
        },
        "1999": {
            "Submissions": [
                {
                    "CASNumber": "67561",
                    "Chemical": "Methanol",
                    "ChemicalNumber": 364,
                    "DCN": "1399135010229",
                    "MaxOnsite": "04",
                    "Pounds": 17800.0,
                    "Score": 4.26786,
                    "SubmissionNumber": 2058914,
                    "Use": "OU"
                },
                {
                    "CASNumber": "108883",
                    "Chemical": "Toluene",
                    "ChemicalNumber": 549,
                    "DCN": "1399135010270",
                    "MaxOnsite": "04",
                    "Pounds": 50041.0,
                    "Score": 8.79198,
                    "SubmissionNumber": 2058918,
                    "Use": "OU"
                },
                {
                    "CASNumber": "108952",
                    "Chemical": "Phenol",
                    "ChemicalNumber": 454,
                    "DCN": "1399135010332",
                    "MaxOnsite": "05",
                    "Pounds": 3100.0,
                    "Score": 0.0,
                    "SubmissionNumber": 2058922,
                    "Use": "P"
                }
            ],
            "TotalPounds": 70941.0,
            "TotalScore": 13.059840000000001,
            "state_score_percentile": 92,
            "us_score_percentile": 82
        },
        "2000": {
            "Submissions": [
                {
                    "CASNumber": "67561",
                    "Chemical": "Methanol",
                    "ChemicalNumber": 364,
                    "DCN": "1300145168922",
                    "MaxOnsite": "04",
                    "Pounds": 14000.0,
                    "Score": 3.4393900000000004,
                    "SubmissionNumber": 85569,
                    "Use": "OU"
                },
                {
                    "CASNumber": "108883",
                    "Chemical": "Toluene",
                    "ChemicalNumber": 549,
                    "DCN": "1300145168934",
                    "MaxOnsite": "04",
                    "Pounds": 39377.0,
                    "Score": 6.79479,
                    "SubmissionNumber": 85570,
                    "Use": "OU"
                },
                {
                    "CASNumber": "108952",
                    "Chemical": "Phenol",
                    "ChemicalNumber": 454,
                    "DCN": "1300145168946",
                    "MaxOnsite": "05",
                    "Pounds": 2675.0,
                    "Score": 0.0,
                    "SubmissionNumber": 85571,
                    "Use": "P"
                }
            ],
            "TotalPounds": 56052.0,
            "TotalScore": 10.23418,
            "state_score_percentile": 90,
            "us_score_percentile": 81
        },
        "2001": {
            "Submissions": [
                {
                    "CASNumber": "108883",
                    "Chemical": "Toluene",
                    "ChemicalNumber": 549,
                    "DCN": "1301155047715",
                    "MaxOnsite": "04",
                    "Pounds": 26293.0,
                    "Score": 4.49076,
                    "SubmissionNumber": 175295,
                    "Use": "OU"
                },
                {
                    "CASNumber": "108952",
                    "Chemical": "Phenol",
                    "ChemicalNumber": 454,
                    "DCN": "1301155110657",
                    "MaxOnsite": "",
                    "Pounds": 2450.0,
                    "Score": 0.0,
                    "SubmissionNumber": 179098,
                    "Use": "P"
                },
                {
                    "CASNumber": "67561",
                    "Chemical": "Methanol",
                    "ChemicalNumber": 364,
                    "DCN": "1301155111178",
                    "MaxOnsite": "04",
                    "Pounds": 12500.0,
                    "Score": 3.1075720000000002,
                    "SubmissionNumber": 179127,
                    "Use": "OU"
                }
            ],
            "TotalPounds": 41243.0,
            "TotalScore": 7.598332,
            "state_score_percentile": 90,
            "us_score_percentile": 80
        },
        "2002": {
            "Submissions": [
                {
                    "CASNumber": "108883",
                    "Chemical": "Toluene",
                    "ChemicalNumber": 549,
                    "DCN": "1302200831372",
                    "MaxOnsite": "04",
                    "Pounds": 8700.0,
                    "Score": 1.5034969999999999,
                    "SubmissionNumber": 268160,
                    "Use": "OU"
                },
                {
                    "CASNumber": "67561",
                    "Chemical": "Methanol",
                    "ChemicalNumber": 364,
                    "DCN": "1302200831509",
                    "MaxOnsite": "04",
                    "Pounds": 4000.0,
                    "Score": 1.013451,
                    "SubmissionNumber": 268173,
                    "Use": "OU"
                },
                {
                    "CASNumber": "108952",
                    "Chemical": "Phenol",
                    "ChemicalNumber": 454,
                    "DCN": "1302200831586",
                    "MaxOnsite": "04",
                    "Pounds": 800.0,
                    "Score": 0.0,
                    "SubmissionNumber": 268181,
                    "Use": "P"
                }
            ],
            "TotalPounds": 13500.0,
            "TotalScore": 2.516948,
            "state_score_percentile": 78,
            "us_score_percentile": 67
        }
    },
    "FIPS": "34023",
    "FRSID": "110000322552",
    "FacilityID": "08901RHNPL298JE",
    "FacilityNumber": 115664,
    "FederalAgencyName": "",
    "FederalFacilityFlag": "C",
    "GridCode": 14,
    "HEM3ID": 14734,
    "LatLongSource": "LRT",
    "LatLongTable": "EPA Geodata",
    "Latitude": 40.485944,
    "Longitude": -74.460361,
    "Method": "GPS CARRIER PHASE STATIC RELATIVE POSITION",
    "MultiplePrimaryNAICS": "F",
    "MultiplePrimarySIC": 0,
    "NAICS1": {
        "1996": {
            "state_count": 22,
            "state_pounds_pct": 77,
            "state_score_pct": 22,
            "us_count": 442,
            "us_pounds_pct": 64,
            "us_score_pct": 21
        },
        "1997": {
            "state_count": 22,
            "state_pounds_pct": 81,
            "state_score_pct": 31,
            "us_count": 444,
            "us_pounds_pct": 68,
            "us_score_pct": 23
        },
        "1998": {
            "state_count": 21,
            "state_pounds_pct": 85,
            "state_score_pct": 23,
            "us_count": 454,
            "us_pounds_pct": 70,
            "us_score_pct": 24
        },
        "1999": {
            "state_count": 23,
            "state_pounds_pct": 78,
            "state_score_pct": 34,
            "us_count": 455,
            "us_pounds_pct": 69,
            "us_score_pct": 24
        },
        "2000": {
            "state_count": 22,
            "state_pounds_pct": 77,
            "state_score_pct": 31,
            "us_count": 470,
            "us_pounds_pct": 68,
            "us_score_pct": 23
        },
        "2001": {
            "state_count": 22,
            "state_pounds_pct": 77,
            "state_score_pct": 31,
            "us_count": 468,
            "us_pounds_pct": 66,
            "us_score_pct": 22
        },
        "2002": {
            "state_count": 20,
            "state_pounds_pct": 75,
            "state_score_pct": 30,
            "us_count": 473,
            "us_pounds_pct": 52,
            "us_score_pct": 16
        },
        "naicscode": "325199",
        "name": "All Other Basic Organic Chemical Manufacturing"
    },
    "NAICSCode3Digit": "325",
    "NAICSCode4Digit": "3251",
    "NAICSCodeSame3Digit": "325",
    "NHDRegion": "",
    "NPDESPermit": "NJG000060",
    "Name": "RHODIA INC.",
    "NearComID": "",
    "NearReach": "",
    "NearStream": "",
    "OnTribalLand": "",
    "ParentDUNS": "002959810",
    "ParentName": "RHODIA INC",
    "PreferredLat": 40.485,
    "PreferredLong": 74.46306,
    "PublicContactName": "DAVID P. TURTLE",
    "PublicContactPhone": "7328461078",
    "RCRANumber": "NJD002184448",
    "RadialDistance": 2797478,
    "ReachSource": "",
    "Region": "2",
    "SIC1": {
        "1996": {
            "state_count": 40,
            "state_pounds_pct": 82,
            "state_score_pct": 20,
            "us_count": 620,
            "us_pounds_pct": 61,
            "us_score_pct": 21
        },
        "1997": {
            "state_count": 37,
            "state_pounds_pct": 86,
            "state_score_pct": 27,
            "us_count": 616,
            "us_pounds_pct": 64,
            "us_score_pct": 22
        },
        "1998": {
            "state_count": 37,
            "state_pounds_pct": 89,
            "state_score_pct": 27,
            "us_count": 619,
            "us_pounds_pct": 67,
            "us_score_pct": 23
        },
        "1999": {
            "state_count": 38,
            "state_pounds_pct": 84,
            "state_score_pct": 34,
            "us_count": 623,
            "us_pounds_pct": 65,
            "us_score_pct": 23
        },
        "2000": {
            "state_count": 36,
            "state_pounds_pct": 83,
            "state_score_pct": 30,
            "us_count": 637,
            "us_pounds_pct": 63,
            "us_score_pct": 22
        },
        "2001": {
            "state_count": 34,
            "state_pounds_pct": 82,
            "state_score_pct": 32,
            "us_count": 642,
            "us_pounds_pct": 62,
            "us_score_pct": 21
        },
        "2002": {
            "state_count": 31,
            "state_pounds_pct": 77,
            "state_score_pct": 22,
            "us_count": 637,
            "us_pounds_pct": 47,
            "us_score_pct": 16
        },
        "name": "Industrial organic chemicals, n.e.c.",
        "siccode": "2869"
    },
    "SICCode2Digit": "28",
    "SICCode3Digit": "286",
    "SICCodeSame2Digit": "28",
    "SK": "",
    "STFIPS": "34",
    "StackDiameter": 0.9144,
    "StackDiameterSource": "SIC 3dig",
    "StackHeight": 7.62,
    "StackHeightSource": "SIC 3dig",
    "StackVelocity": 5.9741,
    "StackVelocitySource": "SIC 3dig",
    "State": "NJ",
    "Street": "298 JERSEY AVE.",
    "SubmitLat": 40.485,
    "SubmitLong": 74.46306,
    "TribalLandName": "",
    "WBANID": "",
    "WaterReleases": "",
    "X": 2216,
    "Y": 2649,
    "ZIP9": "08901",
    "ZIPCode": "08901"
}